{
  "tiers": [
    {
      "groups": [
        {
          "trades": [
            {
              "max_uses": 500,
              "wants": [
                {
                  "item": "zex:9m",
                  "quantity": 8
                }
              ],
              "gives": [
                {
                  "item": "ammo:m1911a",
                  "quantity": 1
                }
              ]
            },
            {
              "max_uses": 500,
              "wants": [
                {
                  "item": "zex:9m",
                  "quantity": 19
                }
              ],
              "gives": [
                {
                  "item": "ammo:glock17a",
                  "quantity": 1
                }
              ]
            },
            {
              "max_uses": 500,
              "wants": [
                {
                  "item": "zex:9m",
                  "quantity": 18
                }
              ],
              "gives": [
                {
                  "item": "ammo:glock18a",
                  "quantity": 1
                }
              ]
            },
            {
              "max_uses": 500,
              "wants": [
                {
                  "item": "zex:9m",
                  "quantity": 15
                }
              ],
              "gives": [
                {
                  "item": "ammo:m9a",
                  "quantity": 1
                }
              ]
            },
            {
              "max_uses": 500,
              "wants": [
                {
                  "item": "zex:9m",
                  "quantity": 30
                }
              ],
              "gives": [
                {
                  "item": "ammo:m10a",
                  "quantity": 1
                }
              ]
            },
            {
              "max_uses": 500,
              "wants": [
                {
                  "item": "zex:9m",
                  "quantity": 40
                }
              ],
              "gives": [
                {
                  "item": "ammo:mp5a",
                  "quantity": 1
                }
              ]
            },
            {
              "max_uses": 500,
              "wants": [
                {
                  "item": "zex:9m",
                  "quantity": 30
                }
              ],
              "gives": [
                {
                  "item": "ammo:mp40a",
                  "quantity": 1
                }
              ]
            },
            {
              "max_uses": 500,
              "wants": [
                {
                  "item": "zex:9m",
                  "quantity": 60
                }
              ],
              "gives": [
                {
                  "item": "ammo:ppsha",
                  "quantity": 1
                }
              ]
            },
            {
              "max_uses": 500,
              "wants": [
                {
                  "item": "zex:9m",
                  "quantity": 30
                }
              ],
              "gives": [
                {
                  "item": "ammo:thoma",
                  "quantity": 1
                }
              ]
            },
            {
              "max_uses": 500,
              "wants": [
                {
                  "item": "zex:9m",
                  "quantity": 30
                }
              ],
              "gives": [
                {
                  "item": "ammo:uzia",
                  "quantity": 1
                }
              ]
            },
            {
              "max_uses": 500,
              "wants": [
                {
                  "item": "zex:9m",
                  "quantity": 20
                }
              ],
              "gives": [
                {
                  "item": "ammo:vz61a",
                  "quantity": 1
                }
              ]
            },
            {
              "max_uses": 500,
              "wants": [
                {
                  "item": "zex:9m",
                  "quantity": 60
                },
                {
                  "item": "zex:9m",
                  "quantity": 10
                }
              ],
              "gives": [
                {
                  "item": "ammo:mg42a",
                  "quantity": 1
                }
              ]
            },
            {
              "max_uses": 500,
              "wants": [
                {
                  "item": "zex:556m",
                  "quantity": 30
                }
              ],
              "gives": [
                {
                  "item": "ammo:ak47a",
                  "quantity": 1
                }
              ]
            },
            {
              "max_uses": 500,
              "wants": [
                {
                  "item": "zex:556m",
                  "quantity": 30
                }
              ],
              "gives": [
                {
                  "item": "ammo:an94a",
                  "quantity": 1
                }
              ]
            },
            {
              "max_uses": 500,
              "wants": [
                {
                  "item": "zex:556m",
                  "quantity": 30
                }
              ],
              "gives": [
                {
                  "item": "ammo:auga",
                  "quantity": 1
                }
              ]
            },
            {
              "max_uses": 500,
              "wants": [
                {
                  "item": "zex:556m",
                  "quantity": 30
                }
              ],
              "gives": [
                {
                  "item": "ammo:g36a",
                  "quantity": 1
                }
              ]
            },
            {
              "max_uses": 500,
              "wants": [
                {
                  "item": "zex:556m",
                  "quantity": 30
                }
              ],
              "gives": [
                {
                  "item": "ammo:hk416a",
                  "quantity": 1
                }
              ]
            },
            {
              "max_uses": 500,
              "wants": [
                {
                  "item": "zex:556m",
                  "quantity": 30
                }
              ],
              "gives": [
                {
                  "item": "ammo:l86a",
                  "quantity": 1
                }
              ]
            },
            {
              "max_uses": 500,
              "wants": [
                {
                  "item": "zex:556m",
                  "quantity": 30
                }
              ],
              "gives": [
                {
                  "item": "ammo:m4a",
                  "quantity": 1
                }
              ]
            },
            {
              "max_uses": 500,
              "wants": [
                {
                  "item": "zex:556m",
                  "quantity": 30
                }
              ],
              "gives": [
                {
                  "item": "ammo:m16a4a",
                  "quantity": 1
                }
              ]
            },
            {
              "max_uses": 500,
              "wants": [
                {
                  "item": "zex:556m",
                  "quantity": 30
                }
              ],
              "gives": [
                {
                  "item": "ammo:scara",
                  "quantity": 1
                }
              ]
            },
            {
              "max_uses": 500,
              "wants": [
                {
                  "item": "zex:556m",
                  "quantity": 30
                }
              ],
              "gives": [
                {
                  "item": "ammo:xm8a",
                  "quantity": 1
                }
              ]
            },
            {
              "max_uses": 500,
              "wants": [
                {
                  "item": "zex:556m",
                  "quantity": 64
                },
                {
                  "item": "zex:556m",
                  "quantity": 36
                }
              ],
              "gives": [
                {
                  "item": "ammo:m249a",
                  "quantity": 1
                }
              ]
            },
            {
              "max_uses": 500,
              "wants": [
                {
                  "item": "zex:556m",
                  "quantity": 64
                },
                {
                  "item": "zex:556m",
                  "quantity": 36
                }
              ],
              "gives": [
                {
                  "item": "ammo:rpka",
                  "quantity": 1
                }
              ]
            },
            {
              "max_uses": 500,
              "wants": [
                {
                  "item": "zex:556m",
                  "quantity": 50
                }
              ],
              "gives": [
                {
                  "item": "ammo:lewisa",
                  "quantity": 1
                }
              ]
            },
           {
              "max_uses": 500,
              "wants": [
                {
                  "item": "zex:762m",
                  "quantity": 5
                }
              ],
              "gives": [
                {
                  "item": "ammo:tt33a",
                  "quantity": 1
                }
              ]
            },
            {
              "max_uses": 500,
              "wants": [
                {
                  "item": "zex:762m",
                  "quantity": 30
                }
              ],
              "gives": [
                {
                  "item": "ammo:bara",
                  "quantity": 1
                }
              ]
            },
            {
              "max_uses": 500,
              "wants": [
                {
                  "item": "zex:762m",
                  "quantity": 30
                }
              ],
              "gives": [
                {
                  "item": "ammo:scarha",
                  "quantity": 1
                }
              ]
            },
            {
              "max_uses": 500,
              "wants": [
                {
                  "item": "zex:762m",
                  "quantity": 50
                }
              ],
              "gives": [
                {
                  "item": "ammo:dp28a",
                  "quantity": 1
                }
              ]
            },
            {
              "max_uses": 500,
              "wants": [
                {
                  "item": "zex:762m",
                  "quantity": 5
                }
              ],
              "gives": [
                {
                  "item": "ammo:awma",
                  "quantity": 1
                }
              ]
            },
            {
              "max_uses": 500,
              "wants": [
                {
                  "item": "zex:762m",
                  "quantity": 5
                }
              ],
              "gives": [
                {
                  "item": "ammo:k98a",
                  "quantity": 1
                }
              ]
            },
            {
              "max_uses": 500,
              "wants": [
                {
                  "item": "zex:762m",
                  "quantity": 10
                }
              ],
              "gives": [
                {
                  "item": "ammo:m82a",
                  "quantity": 1
                }
              ]
            },
            {
              "max_uses": 500,
              "wants": [
                {
                  "item": "zex:762m",
                  "quantity": 10
                }
              ],
              "gives": [
                {
                  "item": "ammo:m110a",
                  "quantity": 1
                }
              ]
            },
            {
              "max_uses": 500,
              "wants": [
                {
                  "item": "zex:762m",
                  "quantity": 5
                }
              ],
              "gives": [
                {
                  "item": "ammo:mosina",
                  "quantity": 1
                }
              ]
            },
            {
              "max_uses": 500,
              "wants": [
                {
                  "item": "zex:762m",
                  "quantity": 10
                }
              ],
              "gives": [
                {
                  "item": "ammo:svda",
                  "quantity": 1
                }
              ]
            },
            {
              "max_uses": 500,
              "wants": [
                {
                  "item": "zex:rocketm",
                  "quantity": 6
                }
              ],
              "gives": [
                {
                  "item": "ammo:famasa",
                  "quantity": 1
                }
              ]
            },
            {
              "max_uses": 500,
              "wants": [
                {
                  "item": "zex:rocketm",
                  "quantity": 16
                }
              ],
              "gives": [
                {
                  "item": "ammo:p90a",
                  "quantity": 1
                }
              ]
            },
            {
              "max_uses": 500,
              "wants": [
                {
                  "item": "zex:rocketm",
                  "quantity": 4
                }
              ],
              "gives": [
                {
                  "item": "ammo:rpga",
                  "quantity": 1
                }
              ]
            },
            {
              "max_uses": 500,
              "wants": [
                {
                  "item": "zex:icecharge",
                  "quantity": 30
                }
              ],
              "gives": [
                {
                  "item": "ammo:sara",
                  "quantity": 1
                }
              ]
            },
            {
              "max_uses": 500,
              "wants": [
                {
                  "item": "zex:btm",
                  "quantity": 4
                }
              ],
              "gives": [
                {
                  "item": "ammo:lazera",
                  "quantity": 1
                }
              ]
            }
          ]
        }
      ]
    }
  ]
}