{"format_version":"1.10.0","geometry.ak47":{"texturewidth":256,"textureheight":256,"visible_bounds_width":10,"visible_bounds_height":10,"visible_bounds_offset":[0,4,0],"bones":[{"name":"root","pivot":[0,0,0]},{"name":"body","parent":"root","pivot":[0,0,0]},{"name":"rightArmA","parent":"root","pivot":[0,0,0]},{"name":"rightArm","parent":"rightArmA","pivot":[-5,22,0]},{"name":"gun","parent":"rightArm","pivot":[-6,-19,-2],"rotation":[0,0,-180]},{"name":"SEX","parent":"gun","pivot":[-11.28581,-111.35038,-4.12068],"cubes":[{"origin":[-7.31029,-120.2,-14.4],"size":[4.6,10,3],"uv":[95,47]},{"origin":[-8.31029,-125.2,-10.59857],"size":[6.6,16,5],"uv":[87,32]},{"origin":[-7,-111.2,-11.59857],"size":[4,1,2],"uv":[112,125]},{"origin":[-6,-98.5,-13.59857],"size":[2,1,4],"uv":[33,254]},{"origin":[-8.31029,-151.11248,-11.59857],"size":[6.6,25.85,6],"uv":[0,226]},{"origin":[-7.31029,-125.26724,-14.41119],"size":[4.6,5,3],"uv":[0,243]},{"origin":[-6.31029,-140.11248,-6.59857],"size":[2.6,1,5],"uv":[0,251]},{"origin":[-6.31029,-147.11248,-1.59857],"size":[2.6,8,1],"uv":[0,248]},{"origin":[-4.31029,-144.11248,-5.59857],"size":[0.6,2,2],"uv":[0,253]},{"origin":[-4.31029,-144.11248,-3.59857],"size":[0.6,1,1],"uv":[0,255]},{"origin":[-7,-118.2,-11.59857],"size":[4,1,2],"uv":[112,125]}]},{"name":"SEX5","parent":"SEX","pivot":[-5.02983,-143.99071,7.82014],"rotation":[-25,0,0],"cubes":[{"origin":[-6.52983,-155.07535,-5.60448],"size":[3,5,13],"uv":[83,0]}]},{"name":"SEX2","parent":"SEX","pivot":[-5.02983,-147.99071,-9.17986],"cubes":[{"origin":[-7.31029,-150.84219,-14.05264],"size":[4.6,5,3],"uv":[3,249]}]},{"name":"SEX6","parent":"SEX","pivot":[-5.02983,-159.99071,-11.17986],"rotation":[22.5,0,0]},{"name":"SEX7","parent":"SEX","pivot":[-5.02983,-158.99071,-5.17986],"rotation":[-65,0,0]},{"name":"SEX4","parent":"SEX","pivot":[-5.02983,-107.99071,7.82014],"rotation":[-40,0,0]},{"name":"SEX3","parent":"SEX","pivot":[-5.02983,-80.99071,9.82014],"rotation":[7.5,0,0]},{"name":"SEX9","parent":"SEX","pivot":[-5.02983,-117.99071,7.82014],"rotation":[30,0,0]},{"name":"dulo","parent":"SEX","pivot":[-4,-97,-9]},{"name":"rotator","parent":"dulo","pivot":[-4,-97,-5]},{"name":"rotate","parent":"rotator","pivot":[-4,-97,-5],"rotation":[0,30,0],"cubes":[{"origin":[-3.7134,-109.2,-6.99641],"size":[1,32,0.5],"uv":[0,225]}]},{"name":"rotate3","parent":"rotator","pivot":[-3,-97,-5],"rotation":[0,60,0],"cubes":[{"origin":[-1.63756,-109.2,-7.01865],"size":[1,32,0.5],"uv":[0,225]}]},{"name":"rotate2","parent":"rotator","pivot":[-1,-97,-5],"rotation":[0,90,0],"cubes":[{"origin":[1.80526,-109.2,-7.63397],"size":[1,32,0.5],"uv":[0,225]}]},{"name":"rotate4","parent":"rotator","pivot":[2,-97,-5],"rotation":[0,120,0],"cubes":[{"origin":[7.86244,-109.2,-8.04352],"size":[1,32,0.5],"uv":[0,225]}]},{"name":"rotate9","parent":"rotator","pivot":[2,-97,-5],"rotation":[0,150,0],"cubes":[{"origin":[9.21481,-109.2,-4.27154],"size":[1,32,0.5],"uv":[0,225]}]},{"name":"rotate10","parent":"rotator","pivot":[2,-97,-5],"rotation":[0,180,0],"cubes":[{"origin":[8.5,-109.2,-0.32872],"size":[1,32,0.5],"uv":[0,225]}]},{"name":"rotator2","parent":"dulo","pivot":[-6,-97,-10],"rotation":[0,180,0]},{"name":"rotate12","parent":"rotator2","pivot":[-5,-97,-10],"rotation":[0,30,0],"cubes":[{"origin":[-6.38468,-109.2,-11.10167],"size":[1,32,0.5],"uv":[0,225]}]},{"name":"rotate13","parent":"rotator2","pivot":[-3,-97,-10],"rotation":[0,60,0],"cubes":[{"origin":[-4.03231,-109.2,-12.94545],"size":[1,32,0.5],"uv":[0,225]}]},{"name":"rotate14","parent":"rotator2","pivot":[0,-97,-10],"rotation":[0,90,0],"cubes":[{"origin":[1.19474,-109.2,-15.63397],"size":[1,32,0.5],"uv":[0,225]}]},{"name":"rotate15","parent":"rotator2","pivot":[0,-97,-10],"rotation":[0,120,0],"cubes":[{"origin":[4.46769,-109.2,-13.84878],"size":[1,32,0.5],"uv":[0,225]}]},{"name":"rotate16","parent":"rotator2","pivot":[0,-97,-10],"rotation":[0,150,0],"cubes":[{"origin":[6.40955,-109.2,-10.66628],"size":[1,32,0.5],"uv":[0,225]}]},{"name":"rotate17","parent":"rotator2","pivot":[0,-97,-10],"rotation":[0,180,0],"cubes":[{"origin":[6.5,-109.2,-6.93923],"size":[1,32,0.5],"uv":[0,225]}]},{"name":"bone","parent":"SEX","pivot":[-6,-39,0],"rotation":[2.5,0,0],"cubes":[{"origin":[-6.52983,-137.17541,-10.8813],"size":[3,7,4],"uv":[0,246]}]},{"name":"bone2","parent":"bone","pivot":[-6,-39,0],"rotation":[5,0,0],"cubes":[{"origin":[-6.52983,-136.17541,-15.8813],"size":[3,7,4],"uv":[0,246]}]},{"name":"bone3","parent":"bone2","pivot":[-6,-39,0],"rotation":[7.5,0,0],"cubes":[{"origin":[-6.52983,-133.7,-24.8813],"size":[3,7,4],"uv":[0,246]}]},{"name":"bone4","parent":"bone3","pivot":[-6,-39,0],"rotation":[10,0,0],"cubes":[{"origin":[-6.52983,-128.6,-36.8813],"size":[3,7,4],"uv":[0,246]}]},{"name":"bone5","parent":"bone4","pivot":[-6,-39,0],"rotation":[10,0,0],"cubes":[{"origin":[-6.52983,-121.5,-47.8813],"size":[3,7,4],"uv":[0,246]}]},{"name":"dulo2","parent":"SEX","pivot":[-4,-147,1]},{"name":"rotator3","parent":"dulo2","pivot":[-4,-147,5]},{"name":"rotate5","parent":"rotator3","pivot":[-4,-147,5],"rotation":[0,30,0]},{"name":"rotate6","parent":"rotator3","pivot":[-3,-147,5],"rotation":[0,60,0]},{"name":"rotate7","parent":"rotator3","pivot":[-1,-147,5],"rotation":[0,90,0],"cubes":[{"origin":[15.80526,-149.2,2.36603],"size":[1,25,0.5],"uv":[0,237]}]},{"name":"rotate8","parent":"rotator3","pivot":[2,-147,5],"rotation":[0,120,0],"cubes":[{"origin":[19.9868,-149.2,8.95648],"size":[1,25,0.5],"uv":[0,237]}]},{"name":"rotate11","parent":"rotator3","pivot":[2,-147,5],"rotation":[0,150,0],"cubes":[{"origin":[16.21481,-149.2,17.85282],"size":[1,25,0.5],"uv":[0,237]}]},{"name":"rotate18","parent":"rotator3","pivot":[2,-147,5],"rotation":[0,180,0],"cubes":[{"origin":[8.5,-149.2,23.67128],"size":[1,25,0.5],"uv":[0,237]}]},{"name":"rotator4","parent":"dulo2","pivot":[-6,-147,0],"rotation":[0,180,0]},{"name":"rotate19","parent":"rotator4","pivot":[-5,-147,0],"rotation":[0,30,0],"cubes":[{"origin":[-13.38468,-149.2,11.02269],"size":[1,25,0.5],"uv":[0,237]}]},{"name":"rotate20","parent":"rotator4","pivot":[-3,-147,0],"rotation":[0,60,0],"cubes":[{"origin":[-16.15667,-149.2,4.05455],"size":[1,25,0.5],"uv":[0,237]}]},{"name":"rotate21","parent":"rotator4","pivot":[0,-147,0],"rotation":[0,90,0],"cubes":[{"origin":[-12.80526,-149.2,-5.63397],"size":[1,25,0.5],"uv":[0,237]}]},{"name":"rotate22","parent":"rotator4","pivot":[0,-147,0],"rotation":[0,120,0]},{"name":"rotate23","parent":"rotator4","pivot":[0,-147,0],"rotation":[0,150,0]},{"name":"rotate24","parent":"rotator4","pivot":[0,-147,0],"rotation":[0,180,0]},{"name":"bone6","parent":"SEX","pivot":[-6,-34,-52],"rotation":[25,0,0]},{"name":"bone7","parent":"bone6","pivot":[0,-20,22]},{"name":"dulo3","parent":"SEX","pivot":[-4,-97,-8]},{"name":"rotator5","parent":"dulo3","pivot":[-4,-97,-4]},{"name":"rotate25","parent":"rotator5","pivot":[-4,-97,-4],"rotation":[0,30,0],"cubes":[{"origin":[-1.2134,-112.2,-10.82654],"size":[1,15,0],"uv":[0,225]}]},{"name":"rotate26","parent":"rotator5","pivot":[-3,-97,-4],"rotation":[0,60,0]},{"name":"rotate27","parent":"rotator5","pivot":[-1,-97,-4],"rotation":[0,90,0],"cubes":[{"origin":[6.80526,-112.2,-7.13397],"size":[1,15,0],"uv":[0,225]}]},{"name":"rotate28","parent":"rotator5","pivot":[2,-97,-4],"rotation":[0,120,0]},{"name":"rotate29","parent":"rotator5","pivot":[2,-97,-4],"rotation":[0,150,0],"cubes":[{"origin":[11.71481,-112.2,0.55859],"size":[1,15,0],"uv":[0,225]}]},{"name":"rotate30","parent":"rotator5","pivot":[2,-97,-4],"rotation":[0,180,0]},{"name":"rotator6","parent":"dulo3","pivot":[-6,-97,-9],"rotation":[0,180,0]},{"name":"rotate31","parent":"rotator6","pivot":[-5,-97,-9],"rotation":[0,30,0],"cubes":[{"origin":[-8.88468,-112.2,-6.27154],"size":[1,15,0],"uv":[0,225]}]},{"name":"rotate32","parent":"rotator6","pivot":[-3,-97,-9],"rotation":[0,60,0]},{"name":"rotate33","parent":"rotator6","pivot":[0,-97,-9],"rotation":[0,90,0],"cubes":[{"origin":[-3.80526,-112.2,-15.13397],"size":[1,15,0],"uv":[0,225]}]},{"name":"rotate34","parent":"rotator6","pivot":[0,-97,-9],"rotation":[0,120,0]},{"name":"rotate35","parent":"rotator6","pivot":[0,-97,-9],"rotation":[0,150,0],"cubes":[{"origin":[3.90955,-112.2,-14.49641],"size":[1,15,0],"uv":[0,225]}]},{"name":"rotate36","parent":"rotator6","pivot":[0,-97,-9],"rotation":[0,180,0]},{"name":"bone14","parent":"SEX","pivot":[-1,-1,0],"cubes":[{"origin":[-7.5,-171.11248,-10.1],"size":[5,2,13],"uv":[0,230]},{"origin":[-6.36603,-168.10551,-6.87749],"size":[2,13,2],"uv":[92,50]},{"origin":[-6.36603,-169.65447,-6.8775],"size":[2,2.00001,9.43826],"uv":[86,41]}]},{"name":"dulo4","parent":"bone14","pivot":[-4,-137,-9]},{"name":"rotator7","parent":"dulo4","pivot":[-4,-136,-5]},{"name":"rotate37","parent":"rotator7","pivot":[-4,-136,-5],"rotation":[0,30,0],"cubes":[{"origin":[-3.7134,-169.2,-9.99641],"size":[1,18,3.5],"uv":[100,30]}]},{"name":"rotate38","parent":"rotator7","pivot":[-3,-136,-5],"rotation":[0,60,0],"cubes":[{"origin":[-1.63756,-169.2,-10.01865],"size":[1,18,3.5],"uv":[100,30]}]},{"name":"rotate39","parent":"rotator7","pivot":[-1,-136,-5],"rotation":[0,90,0],"cubes":[{"origin":[1.80526,-169.2,-10.63397],"size":[1,18,3.5],"uv":[100,30]}]},{"name":"rotate40","parent":"rotator7","pivot":[2,-136,-5],"rotation":[0,120,0],"cubes":[{"origin":[7.86244,-169.2,-11.04352],"size":[1,18,3.5],"uv":[100,30]}]},{"name":"rotate41","parent":"rotator7","pivot":[2,-136,-5],"rotation":[0,150,0],"cubes":[{"origin":[9.21481,-169.2,-7.27154],"size":[1,18,3.5],"uv":[100,30]}]},{"name":"rotate42","parent":"rotator7","pivot":[2,-136,-5],"rotation":[0,180,0],"cubes":[{"origin":[8.5,-169.2,-3.32872],"size":[1,18,3.5],"uv":[100,30]}]},{"name":"rotator8","parent":"dulo4","pivot":[-6,-136,-10],"rotation":[0,180,0]},{"name":"rotate43","parent":"rotator8","pivot":[-5,-136,-10],"rotation":[0,30,0],"cubes":[{"origin":[-6.38468,-169.2,-14.10167],"size":[1,18,3.5],"uv":[100,30]}]},{"name":"rotate44","parent":"rotator8","pivot":[-3,-136,-10],"rotation":[0,60,0],"cubes":[{"origin":[-4.03231,-169.2,-15.94545],"size":[1,18,3.5],"uv":[100,30]}]},{"name":"rotate45","parent":"rotator8","pivot":[0,-136,-10],"rotation":[0,90,0],"cubes":[{"origin":[1.19474,-169.2,-18.63397],"size":[1,18,3.5],"uv":[100,30]}]},{"name":"rotate46","parent":"rotator8","pivot":[0,-136,-10],"rotation":[0,120,0],"cubes":[{"origin":[4.46769,-169.2,-16.84878],"size":[1,18,3.5],"uv":[100,30]}]},{"name":"rotate47","parent":"rotator8","pivot":[0,-136,-10],"rotation":[0,150,0],"cubes":[{"origin":[6.40955,-169.2,-13.66628],"size":[1,18,3.5],"uv":[100,30]}]},{"name":"rotate48","parent":"rotator8","pivot":[0,-136,-10],"rotation":[0,180,0],"cubes":[{"origin":[6.5,-169.2,-9.93923],"size":[1,15,4.5],"uv":[100,30]}]},{"name":"bone8","parent":"bone14","pivot":[0,-154,-2],"rotation":[30,0,0],"cubes":[{"origin":[-6.36603,-168.10551,-6.87749],"size":[2,19,2],"uv":[110,33]}]},{"name":"leftArmA","parent":"root","pivot":[5,22,0]},{"name":"leftArm","parent":"leftArmA","pivot":[5,22,0]}]}}