{
	"format_version": "1.12.0",
	"minecraft:geometry": [
		{
			"description": {
				"identifier": "geometry.m16a4",
				"texture_width": 64,
				"texture_height": 32,
				"visible_bounds_width": 29,
				"visible_bounds_height": 31,
				"visible_bounds_offset": [0, 1.5, 0]
			},
			"bones": [
				{
					"name": "root",
					"pivot": [0, 0, 0]
				},
				{
					"name": "body",
					"parent": "root",
					"pivot": [0, 0, 0]
				},
				{
					"name": "rightArmA",
					"parent": "root",
					"pivot": [0, 0, 0]
				},
				{
					"name": "rightArm",
					"parent": "rightArmA",
					"pivot": [-5, 22, 0]
				},
				{
					"name": "gun",
					"parent": "rightArm",
					"pivot": [-5.9, -19, -2],
					"rotation": [0, 0, -180]
				},
				{
					"name": "guncube",
					"parent": "gun",
					"pivot": [-4.72, -100.67078, -16.0432],
					"cubes": [
						{
							"origin": [-7.1, -155.5623, -7.80869],
							"size": [5, 3.78804, 3.50346],
							"pivot": [-5.2, -152.77426, -5.30869],
							"rotation": [-30, 0, 0],
							"uv": {
								"north": {"uv": [24, 13], "uv_size": [14, -11]},
								"east": {"uv": [24, 2], "uv_size": [3, 5]},
								"south": {"uv": [24, 2], "uv_size": [13, 9]},
								"west": {"uv": [24, 2], "uv_size": [3, 5]},
								"up": {"uv": [24, 11], "uv_size": [10, -9]},
								"down": {"uv": [24, 2], "uv_size": [10, 9]}
							}
						},
						{
							"origin": [-7.1, -148.00824, -0.44266],
							"size": [5, 6.25, 0.5],
							"uv": {
								"north": {"uv": [24, 15], "uv_size": [14, -11]},
								"east": {"uv": [24, 4], "uv_size": [3, 5]},
								"south": {"uv": [24, 4], "uv_size": [13, 9]},
								"west": {"uv": [24, 4], "uv_size": [3, 5]},
								"up": {"uv": [24, 13], "uv_size": [10, -9]},
								"down": {"uv": [24, 4], "uv_size": [10, 9]}
							}
						},
						{
							"origin": [-7.6, -141.34883, -1.52975],
							"size": [6, 8.9, 1],
							"pivot": [-5.2, -138.94883, -1.52975],
							"rotation": [15, 0, 0],
							"uv": {
								"north": {"uv": [24, 13], "uv_size": [14, -11]},
								"east": {"uv": [24, 2], "uv_size": [3, 5]},
								"south": {"uv": [24, 2], "uv_size": [13, 9]},
								"west": {"uv": [24, 2], "uv_size": [3, 5]},
								"up": {"uv": [24, 11], "uv_size": [10, -9]},
								"down": {"uv": [24, 2], "uv_size": [10, 9]}
							}
						},
						{
							"origin": [-7.35, -141.29446, -7.36674],
							"size": [5.5, 8.4, 5.25],
							"uv": {
								"north": {"uv": [24, 13], "uv_size": [14, -11]},
								"east": {"uv": [24, 2], "uv_size": [3, 5]},
								"south": {"uv": [24, 2], "uv_size": [13, 9]},
								"west": {"uv": [24, 2], "uv_size": [3, 5]},
								"up": {"uv": [24, 11], "uv_size": [10, -9]},
								"down": {"uv": [24, 2], "uv_size": [10, 9]}
							}
						},
						{
							"origin": [-7.1, -152.40824, -7.34266],
							"size": [5, 11.4, 3.4],
							"uv": {
								"north": {"uv": [24, 13], "uv_size": [14, -11]},
								"east": {"uv": [24, 2], "uv_size": [3, 5]},
								"south": {"uv": [24, 2], "uv_size": [13, 9]},
								"west": {"uv": [24, 2], "uv_size": [3, 5]},
								"up": {"uv": [24, 11], "uv_size": [10, -9]},
								"down": {"uv": [24, 2], "uv_size": [10, 9]}
							}
						},
						{
							"origin": [-7.35, -143.79446, -7.36674],
							"size": [5.5, 3.15, 3],
							"uv": {
								"north": {"uv": [24, 13], "uv_size": [14, -11]},
								"east": {"uv": [24, 2], "uv_size": [3, 5]},
								"south": {"uv": [24, 2], "uv_size": [13, 9]},
								"west": {"uv": [24, 2], "uv_size": [3, 5]},
								"up": {"uv": [24, 11], "uv_size": [10, -9]},
								"down": {"uv": [24, 2], "uv_size": [10, 9]}
							}
						},
						{
							"origin": [-7.6, -141.29446, -1.01674],
							"size": [6, 0.4, 1.1],
							"uv": {
								"north": {"uv": [24, 13], "uv_size": [14, -11]},
								"east": {"uv": [24, 2], "uv_size": [3, 5]},
								"south": {"uv": [24, 2], "uv_size": [13, 9]},
								"west": {"uv": [24, 2], "uv_size": [3, 5]},
								"up": {"uv": [24, 11], "uv_size": [10, -9]},
								"down": {"uv": [24, 2], "uv_size": [10, 9]}
							}
						},
						{
							"origin": [-7.35, -132.89446, -7.36674],
							"size": [5.5, 1.25, 1.25],
							"uv": {
								"north": {"uv": [24, 13], "uv_size": [14, -11]},
								"east": {"uv": [24, 2], "uv_size": [3, 5]},
								"south": {"uv": [24, 2], "uv_size": [13, 9]},
								"west": {"uv": [24, 2], "uv_size": [3, 5]},
								"up": {"uv": [24, 11], "uv_size": [10, -9]},
								"down": {"uv": [24, 2], "uv_size": [10, 9]}
							}
						},
						{
							"origin": [-7.35, -141.29446, -3.36674],
							"size": [5.5, 0.4, 3.25],
							"uv": {
								"north": {"uv": [24, 13], "uv_size": [14, -11]},
								"east": {"uv": [24, 2], "uv_size": [3, 5]},
								"south": {"uv": [24, 2], "uv_size": [13, 9]},
								"west": {"uv": [24, 2], "uv_size": [3, 5]},
								"up": {"uv": [24, 11], "uv_size": [10, -9]},
								"down": {"uv": [24, 2], "uv_size": [10, 9]}
							}
						},
						{
							"origin": [-7.45, -132.64446, -7.11674],
							"size": [5.7, 0.75, 0.75],
							"uv": {
								"north": {"uv": [44, 14], "uv_size": [14, -11]},
								"east": {"uv": [44, 3], "uv_size": [3, 5]},
								"south": {"uv": [44, 3], "uv_size": [13, 9]},
								"west": {"uv": [44, 3], "uv_size": [3, 5]},
								"up": {"uv": [44, 12], "uv_size": [10, -9]},
								"down": {"uv": [44, 3], "uv_size": [10, 9]}
							}
						},
						{
							"origin": [-7.6, -133.64446, -3.36674],
							"size": [6, 1.25, 1.25],
							"uv": {
								"north": {"uv": [24, 13], "uv_size": [14, -11]},
								"east": {"uv": [24, 2], "uv_size": [3, 5]},
								"south": {"uv": [24, 2], "uv_size": [13, 9]},
								"west": {"uv": [24, 2], "uv_size": [3, 5]},
								"up": {"uv": [24, 11], "uv_size": [10, -9]},
								"down": {"uv": [24, 2], "uv_size": [10, 9]}
							}
						},
						{
							"origin": [-7.35, -141.06261, -2.70383],
							"size": [5.5, 8.11378, 2.17408],
							"pivot": [-5.2, -138.94883, -1.52975],
							"rotation": [15, 0, 0],
							"uv": {
								"north": {"uv": [24, 13], "uv_size": [14, -11]},
								"east": {"uv": [24, 2], "uv_size": [3, 5]},
								"south": {"uv": [24, 2], "uv_size": [13, 9]},
								"west": {"uv": [24, 2], "uv_size": [3, 5]},
								"up": {"uv": [24, 11], "uv_size": [10, -9]},
								"down": {"uv": [24, 2], "uv_size": [10, 9]}
							}
						},
						{
							"origin": [-7.35, -152.15824, -5.94266],
							"size": [0.25, 1.15, 0.5],
							"uv": {
								"north": {"uv": [24, 13], "uv_size": [14, -11]},
								"east": {"uv": [24, 2], "uv_size": [3, 5]},
								"south": {"uv": [24, 2], "uv_size": [13, 9]},
								"west": {"uv": [24, 2], "uv_size": [3, 5]},
								"up": {"uv": [24, 11], "uv_size": [10, -9]},
								"down": {"uv": [24, 2], "uv_size": [10, 9]}
							}
						},
						{
							"origin": [-7.45, -152.40824, -3.94266],
							"size": [5.7, 4.4, 4],
							"uv": {
								"north": {"uv": [45, 13], "uv_size": [14, -11]},
								"east": {"uv": [45, 2], "uv_size": [3, 5]},
								"south": {"uv": [45, 2], "uv_size": [13, 9]},
								"west": {"uv": [45, 2], "uv_size": [3, 5]},
								"up": {"uv": [45, 11], "uv_size": [10, -9]},
								"down": {"uv": [45, 2], "uv_size": [10, 9]}
							}
						},
						{
							"origin": [-7.35, -150.90824, -6.19266],
							"size": [0.25, 1.15, 1],
							"uv": {
								"north": {"uv": [45, 13], "uv_size": [14, -11]},
								"east": {"uv": [45, 2], "uv_size": [3, 5]},
								"south": {"uv": [45, 2], "uv_size": [13, 9]},
								"west": {"uv": [45, 2], "uv_size": [3, 5]},
								"up": {"uv": [45, 11], "uv_size": [10, -9]},
								"down": {"uv": [45, 2], "uv_size": [10, 9]}
							}
						},
						{
							"origin": [-7.35, -149.65824, -5.94266],
							"size": [0.25, 1.15, 0.5],
							"uv": {
								"north": {"uv": [24, 13], "uv_size": [14, -11]},
								"east": {"uv": [24, 2], "uv_size": [3, 5]},
								"south": {"uv": [24, 2], "uv_size": [13, 9]},
								"west": {"uv": [24, 2], "uv_size": [3, 5]},
								"up": {"uv": [24, 11], "uv_size": [10, -9]},
								"down": {"uv": [24, 2], "uv_size": [10, 9]}
							}
						},
						{
							"origin": [-7.35, -150.55824, -5.19266],
							"size": [0.25, 0.45, 1],
							"uv": {
								"north": {"uv": [45, 13], "uv_size": [14, -11]},
								"east": {"uv": [45, 2], "uv_size": [3, 5]},
								"south": {"uv": [45, 2], "uv_size": [13, 9]},
								"west": {"uv": [45, 2], "uv_size": [3, 5]},
								"up": {"uv": [45, 11], "uv_size": [10, -9]},
								"down": {"uv": [45, 2], "uv_size": [10, 9]}
							}
						},
						{
							"origin": [-7.1, -148.00824, -3.94266],
							"size": [5, 1, 4],
							"uv": {
								"north": {"uv": [25, 14], "uv_size": [14, -11]},
								"east": {"uv": [25, 3], "uv_size": [3, 5]},
								"south": {"uv": [25, 3], "uv_size": [13, 9]},
								"west": {"uv": [27, 5], "uv_size": [3, 5]},
								"up": {"uv": [25, 12], "uv_size": [10, -9]},
								"down": {"uv": [25, 3], "uv_size": [10, 9]}
							}
						},
						{
							"origin": [-7.1, -146.00824, -6.14266],
							"size": [5, 1, 1.95],
							"pivot": [-5.2, -148.00824, -5.94266],
							"rotation": [-45, 0, 0],
							"uv": {
								"north": {"uv": [25, 14], "uv_size": [14, -11]},
								"east": {"uv": [25, 3], "uv_size": [3, 5]},
								"south": {"uv": [25, 3], "uv_size": [13, 9]},
								"west": {"uv": [27, 5], "uv_size": [3, 5]},
								"up": {"uv": [25, 12], "uv_size": [10, -9]},
								"down": {"uv": [25, 3], "uv_size": [10, 9]}
							}
						},
						{
							"origin": [-7.1, -142.00824, -3.94266],
							"size": [5, 1, 4],
							"uv": {
								"north": {"uv": [25, 14], "uv_size": [14, -11]},
								"east": {"uv": [25, 3], "uv_size": [3, 5]},
								"south": {"uv": [25, 3], "uv_size": [13, 9]},
								"west": {"uv": [27, 5], "uv_size": [3, 5]},
								"up": {"uv": [25, 12], "uv_size": [10, -9]},
								"down": {"uv": [25, 3], "uv_size": [10, 9]}
							}
						},
						{
							"origin": [-7.1, -147.00824, 0.55734],
							"size": [5, 1, 1.2],
							"pivot": [-5.2, -149.00824, 0.75734],
							"rotation": [45, 0, 0],
							"uv": {
								"north": {"uv": [25, 14], "uv_size": [14, -11]},
								"east": {"uv": [25, 3], "uv_size": [3, 5]},
								"south": {"uv": [25, 3], "uv_size": [13, 9]},
								"west": {"uv": [27, 5], "uv_size": [3, 5]},
								"up": {"uv": [25, 12], "uv_size": [10, -9]},
								"down": {"uv": [25, 3], "uv_size": [10, 9]}
							}
						},
						{
							"origin": [-7.1, -146.50824, 1.75734],
							"size": [5, 0.5, 0.5],
							"pivot": [-5.2, -149.00824, 0.75734],
							"rotation": [45, 0, 0],
							"uv": {
								"north": {"uv": [25, 14], "uv_size": [14, -11]},
								"east": {"uv": [25, 3], "uv_size": [3, 5]},
								"south": {"uv": [25, 3], "uv_size": [13, 9]},
								"west": {"uv": [27, 5], "uv_size": [3, 5]},
								"up": {"uv": [25, 12], "uv_size": [10, -9]},
								"down": {"uv": [25, 3], "uv_size": [10, 9]}
							}
						},
						{
							"origin": [-7.1, -139.00824, 1.85734],
							"size": [5, 1, 1.45],
							"pivot": [-5.2, -141.00824, 1.55734],
							"rotation": [135, 0, 0],
							"uv": {
								"north": {"uv": [25, 14], "uv_size": [14, -11]},
								"east": {"uv": [25, 3], "uv_size": [3, 5]},
								"south": {"uv": [25, 3], "uv_size": [13, 9]},
								"west": {"uv": [27, 5], "uv_size": [3, 5]},
								"up": {"uv": [25, 12], "uv_size": [10, -9]},
								"down": {"uv": [25, 3], "uv_size": [10, 9]}
							}
						},
						{
							"origin": [-7.1, -138.00824, -5.14266],
							"size": [5, 1, 1.95],
							"pivot": [-5.2, -140.00824, -4.94266],
							"rotation": [-135, 0, 0],
							"uv": {
								"north": {"uv": [25, 14], "uv_size": [14, -11]},
								"east": {"uv": [25, 3], "uv_size": [3, 5]},
								"south": {"uv": [25, 3], "uv_size": [13, 9]},
								"west": {"uv": [27, 5], "uv_size": [3, 5]},
								"up": {"uv": [25, 12], "uv_size": [10, -9]},
								"down": {"uv": [25, 3], "uv_size": [10, 9]}
							}
						},
						{
							"origin": [-7.1, -138.50824, 1.40734],
							"size": [5, 0.5, 0.45],
							"pivot": [-5.2, -141.00824, 1.55734],
							"rotation": [135, 0, 0],
							"uv": {
								"north": {"uv": [25, 14], "uv_size": [14, -11]},
								"east": {"uv": [25, 3], "uv_size": [3, 5]},
								"south": {"uv": [25, 3], "uv_size": [13, 9]},
								"west": {"uv": [27, 5], "uv_size": [3, 5]},
								"up": {"uv": [25, 12], "uv_size": [10, -9]},
								"down": {"uv": [25, 3], "uv_size": [10, 9]}
							}
						}
					]
				},
				{
					"name": "bone32",
					"parent": "guncube",
					"pivot": [-4.6, -140.55181, -0.927],
					"cubes": [
						{
							"origin": [-5.1, -144.96603, -4.65923],
							"size": [1, 1, 1.25],
							"uv": {
								"north": {"uv": [27, 2.5], "uv_size": [9, 4]},
								"east": {"uv": [28, 1.5], "uv_size": [8, 4]},
								"south": {"uv": [43, 2], "uv_size": [9, 4]},
								"west": {"uv": [26, 1], "uv_size": [11, 6.5]},
								"up": {"uv": [26, 1.5], "uv_size": [12, 5.5]},
								"down": {"uv": [28, 6.5], "uv_size": [11, -4.5]}
							}
						},
						{
							"origin": [-5.1, -145.86247, -5.32344],
							"size": [1, 1.5, 1.25],
							"pivot": [-4.6, -145.46603, -4.46989],
							"rotation": [-45, 0, 0],
							"uv": {
								"north": {"uv": [27, 2.5], "uv_size": [9, 4]},
								"east": {"uv": [28, 1.5], "uv_size": [8, 4]},
								"south": {"uv": [24, 2], "uv_size": [9, 4]},
								"west": {"uv": [26, 1], "uv_size": [11, 6.5]},
								"up": {"uv": [26, 1.5], "uv_size": [12, 5.5]},
								"down": {"uv": [28, 6.5], "uv_size": [11, -4.5]}
							}
						},
						{
							"origin": [-4.9, -145.06603, -4.65923],
							"size": [0.6, 0.55, 3.25],
							"uv": {
								"north": {"uv": [27, 2.5], "uv_size": [9, 4]},
								"east": {"uv": [28, 1.5], "uv_size": [8, 4]},
								"south": {"uv": [43, 2], "uv_size": [9, 4]},
								"west": {"uv": [26, 1], "uv_size": [11, 6.5]},
								"up": {"uv": [26, 1.5], "uv_size": [12, 5.5]},
								"down": {"uv": [28, 6.5], "uv_size": [11, -4.5]}
							}
						},
						{
							"origin": [-4.9, -144.92525, -4.72059],
							"size": [0.6, 0.55, 3.25],
							"pivot": [-4.6, -145.14835, -3.05201],
							"rotation": [-5, 0, 0],
							"uv": {
								"north": {"uv": [27, 2.5], "uv_size": [9, 4]},
								"east": {"uv": [28, 1.5], "uv_size": [8, 4]},
								"south": {"uv": [43, 2], "uv_size": [9, 4]},
								"west": {"uv": [26, 1], "uv_size": [11, 6.5]},
								"up": {"uv": [26, 1.5], "uv_size": [12, 5.5]},
								"down": {"uv": [28, 6.5], "uv_size": [11, -4.5]}
							}
						},
						{
							"origin": [-5.1, -144.86247, -5.32344],
							"size": [1, 1.5, 1.25],
							"pivot": [-4.6, -144.46603, -4.46989],
							"rotation": [-45, 0, 0],
							"uv": {
								"north": {"uv": [27, 2.5], "uv_size": [9, 4]},
								"east": {"uv": [28, 1.5], "uv_size": [8, 4]},
								"south": {"uv": [43, 2], "uv_size": [9, 4]},
								"west": {"uv": [26, 1], "uv_size": [11, 6.5]},
								"up": {"uv": [26, 1.5], "uv_size": [12, 5.5]},
								"down": {"uv": [28, 6.5], "uv_size": [11, -4.5]}
							}
						},
						{
							"origin": [-4.9, -144.0061, -1.81395],
							"size": [0.6, 0.3, 1],
							"pivot": [-4.6, -144.08466, -0.5425],
							"rotation": [45, 0, 0],
							"uv": {
								"north": {"uv": [27, 2.5], "uv_size": [9, 4]},
								"east": {"uv": [28, 1.5], "uv_size": [8, 4]},
								"south": {"uv": [43, 2], "uv_size": [9, 4]},
								"west": {"uv": [26, 1], "uv_size": [11, 6.5]},
								"up": {"uv": [26, 1.5], "uv_size": [12, 5.5]},
								"down": {"uv": [28, 6.5], "uv_size": [11, -4.5]}
							}
						},
						{
							"origin": [-4.9, -144.14397, -1.72608],
							"size": [0.6, 0.3, 1],
							"pivot": [-4.6, -144.22252, -0.45464],
							"rotation": [45, 0, 0],
							"uv": {
								"north": {"uv": [27, 2.5], "uv_size": [9, 4]},
								"east": {"uv": [28, 1.5], "uv_size": [8, 4]},
								"south": {"uv": [43, 2], "uv_size": [9, 4]},
								"west": {"uv": [26, 1], "uv_size": [11, 6.5]},
								"up": {"uv": [26, 1.5], "uv_size": [12, 5.5]},
								"down": {"uv": [28, 6.5], "uv_size": [11, -4.5]}
							}
						},
						{
							"origin": [-4.9, -143.50891, -2.10212],
							"size": [0.6, 0.3, 0.35],
							"pivot": [-4.6, -143.23391, -0.97712],
							"rotation": [90, 0, 0],
							"uv": {
								"north": {"uv": [26, 2.5], "uv_size": [9, 4]},
								"east": {"uv": [27, 1.5], "uv_size": [8, 4]},
								"south": {"uv": [27, 1], "uv_size": [9, 4]},
								"west": {"uv": [25, 1], "uv_size": [11, 6.5]},
								"up": {"uv": [25, 1.5], "uv_size": [12, 5.5]},
								"down": {"uv": [27, 6.5], "uv_size": [11, -4.5]}
							}
						}
					]
				},
				{
					"name": "guncube4",
					"parent": "guncube",
					"pivot": [-6.12983, -73.49071, 16.82014]
				},
				{
					"name": "guncuberitzel_1",
					"parent": "guncube4",
					"pivot": [-7.1, -35.5, -1]
				},
				{
					"name": "guncuberitzel8",
					"parent": "guncuberitzel_1",
					"pivot": [-7.1, -35.5, -13],
					"rotation": [0, -135, 0],
					"cubes": [
						{
							"origin": [-6.20218, -131.73246, -18.73432],
							"size": [4, 25, 3],
							"uv": {
								"north": {"uv": [59, 13], "uv_size": [-3, -4]},
								"east": {"uv": [0, 0], "uv_size": [3, 19]},
								"south": {"uv": [59, 13], "uv_size": [-3, -4]},
								"west": {"uv": [0, 0], "uv_size": [3, 19]},
								"up": {"uv": [59, 9], "uv_size": [-3, -9]},
								"down": {"uv": [59, 0], "uv_size": [-3, 9]}
							}
						}
					]
				},
				{
					"name": "guncuberitzel7",
					"parent": "guncuberitzel_1",
					"pivot": [-7.1, -35.5, -13],
					"rotation": [0, -90, 0],
					"cubes": [
						{
							"origin": [-3.58194, -131.73246, -16.59149],
							"size": [4, 25, 3],
							"uv": {
								"north": {"uv": [59, 13], "uv_size": [-3, -4]},
								"east": {"uv": [59, 13], "uv_size": [-3, -4]},
								"south": {"uv": [59, 13], "uv_size": [-3, -4]},
								"west": {"uv": [50, 0], "uv_size": [3, 16]},
								"up": {"uv": [59, 9], "uv_size": [-3, -9]},
								"down": {"uv": [59, 0], "uv_size": [-3, 9]}
							}
						},
						{
							"origin": [-3.58194, -131.73246, -16.59149],
							"size": [4.5, 24, 3],
							"uv": {
								"north": {"uv": [59, 13], "uv_size": [-3, -4]},
								"east": {"uv": [59, 13], "uv_size": [-3, -4]},
								"south": {"uv": [59, 13], "uv_size": [-3, -4]},
								"west": {"uv": [50, 0], "uv_size": [3, 16]},
								"up": {"uv": [59, 9], "uv_size": [-3, -9]},
								"down": {"uv": [59, 0], "uv_size": [-3, 9]}
							}
						}
					]
				},
				{
					"name": "guncuberitzel6",
					"parent": "guncuberitzel_1",
					"pivot": [-7.1, -35.5, 15],
					"rotation": [0, -45, 0],
					"cubes": [
						{
							"origin": [-23.04335, -131.73246, -5.02249],
							"size": [4, 25, 3],
							"uv": {
								"north": {"uv": [59, 13], "uv_size": [-3, -4]},
								"east": {"uv": [0, 0], "uv_size": [3, 19]},
								"south": {"uv": [59, 13], "uv_size": [-3, -4]},
								"west": {"uv": [0, 0], "uv_size": [3, 19]},
								"up": {"uv": [59, 9], "uv_size": [-3, -9]},
								"down": {"uv": [59, 0], "uv_size": [-3, 9]}
							}
						}
					]
				},
				{
					"name": "guncuberitzel5",
					"parent": "guncuberitzel_1",
					"pivot": [-7.1, -35.5, -13],
					"cubes": [
						{
							"origin": [-4.38719, -131.73246, -10.60326],
							"size": [3, 25, 3],
							"uv": {
								"north": {"uv": [59, 13], "uv_size": [-3, -4]},
								"east": {"uv": [59, 13], "uv_size": [-3, -4]},
								"south": {"uv": [59, 13], "uv_size": [-3, -4]},
								"west": {"uv": [48, 1], "uv_size": [3, 13]},
								"up": {"uv": [59, 9], "uv_size": [-3, -9]},
								"down": {"uv": [59, 0], "uv_size": [-3, 9]}
							}
						},
						{
							"origin": [-4.38719, -131.73246, -10.60326],
							"size": [3.5, 24, 3],
							"uv": {
								"north": {"uv": [59, 13], "uv_size": [-3, -4]},
								"east": {"uv": [59, 13], "uv_size": [-3, -4]},
								"south": {"uv": [59, 13], "uv_size": [-3, -4]},
								"west": {"uv": [48, 1], "uv_size": [3, 13]},
								"up": {"uv": [59, 9], "uv_size": [-3, -9]},
								"down": {"uv": [59, 0], "uv_size": [-3, 9]}
							}
						}
					]
				},
				{
					"name": "guncuberitzel4",
					"parent": "guncuberitzel_1",
					"pivot": [-7.1, -35.5, -13],
					"rotation": [0, -135, 0],
					"cubes": [
						{
							"origin": [-9.44482, -131.73246, -18.73432],
							"size": [4, 25, 3],
							"uv": {
								"north": {"uv": [59, 13], "uv_size": [-3, -4]},
								"east": {"uv": [0, 0], "uv_size": [3, 19]},
								"south": {"uv": [59, 13], "uv_size": [-3, -4]},
								"west": {"uv": [0, 0], "uv_size": [3, 19]},
								"up": {"uv": [59, 9], "uv_size": [-3, -9]},
								"down": {"uv": [59, 0], "uv_size": [-3, 9]}
							}
						}
					]
				},
				{
					"name": "guncuberitzel3",
					"parent": "guncuberitzel_1",
					"pivot": [-11.1, -35.5, -13],
					"rotation": [0, -90, 0],
					"cubes": [
						{
							"origin": [-10.82458, -131.73246, -20.59149],
							"size": [4, 25, 3],
							"uv": {
								"north": {"uv": [59, 13], "uv_size": [-3, -4]},
								"east": {"uv": [59, 13], "uv_size": [-3, -4]},
								"south": {"uv": [59, 13], "uv_size": [-3, -4]},
								"west": {"uv": [7, 3], "uv_size": [3, 32]},
								"up": {"uv": [59, 9], "uv_size": [-3, -9]},
								"down": {"uv": [59, 0], "uv_size": [-3, 9]}
							}
						},
						{
							"origin": [-11.32458, -131.73246, -20.59149],
							"size": [4.5, 24, 3],
							"uv": {
								"north": {"uv": [59, 13], "uv_size": [-3, -4]},
								"east": {"uv": [59, 13], "uv_size": [-3, -4]},
								"south": {"uv": [59, 13], "uv_size": [-3, -4]},
								"west": {"uv": [7, 3], "uv_size": [3, 32]},
								"up": {"uv": [59, 9], "uv_size": [-3, -9]},
								"down": {"uv": [59, 0], "uv_size": [-3, 9]}
							}
						}
					]
				},
				{
					"name": "guncuberitzel2",
					"parent": "guncuberitzel_1",
					"pivot": [-7.1, -35.5, -9],
					"rotation": [0, -45, 0],
					"cubes": [
						{
							"origin": [-9.31543, -131.73246, -12.05192],
							"size": [4, 25, 3],
							"uv": {
								"north": {"uv": [59, 13], "uv_size": [-3, -4]},
								"east": {"uv": [0, 0], "uv_size": [3, 19]},
								"south": {"uv": [59, 13], "uv_size": [-3, -4]},
								"west": {"uv": [0, 0], "uv_size": [3, 19]},
								"up": {"uv": [59, 9], "uv_size": [-3, -9]},
								"down": {"uv": [59, 0], "uv_size": [-3, 9]}
							}
						}
					]
				},
				{
					"name": "guncuberitzel",
					"parent": "guncuberitzel_1",
					"pivot": [-7.1, -35.5, -1],
					"cubes": [
						{
							"origin": [-8.62983, -131.73246, -10.60326],
							"size": [5, 25, 3],
							"uv": {
								"north": {"uv": [59, 13], "uv_size": [-3, -4]},
								"east": {"uv": [48, 4], "uv_size": [7, 14]},
								"south": {"uv": [59, 13], "uv_size": [-3, -4]},
								"west": {"uv": [8, 3], "uv_size": [3, 32]},
								"up": {"uv": [59, 9], "uv_size": [-3, -9]},
								"down": {"uv": [59, 0], "uv_size": [-3, 9]}
							}
						},
						{
							"origin": [-9.12983, -131.73246, -10.60326],
							"size": [5.5, 24, 3],
							"uv": {
								"north": {"uv": [59, 13], "uv_size": [-3, -4]},
								"east": {"uv": [48, 4], "uv_size": [7, 14]},
								"south": {"uv": [59, 13], "uv_size": [-3, -4]},
								"west": {"uv": [8, 3], "uv_size": [3, 32]},
								"up": {"uv": [59, 9], "uv_size": [-3, -9]},
								"down": {"uv": [59, 0], "uv_size": [-3, 9]}
							}
						}
					]
				},
				{
					"name": "bone9",
					"parent": "guncube",
					"pivot": [-0.1, 0, -2],
					"cubes": [
						{
							"origin": [-7.1, -155.6905, -10.50869],
							"size": [5, 23.98778, 3.275],
							"uv": {
								"north": {"uv": [22, 13.5], "uv_size": [16, -7]},
								"east": {"uv": [22, 13.5], "uv_size": [16, -13.5]},
								"south": {"uv": [22, 13.5], "uv_size": [16, -7]},
								"west": {"uv": [22, 13.5], "uv_size": [16, -13.5]},
								"up": {"uv": [22, 9.5], "uv_size": [12, -9.5]},
								"down": {"uv": [22, 0], "uv_size": [12, 9.5]}
							}
						},
						{
							"origin": [-1.38319, -155.6905, -21.89219],
							"size": [2, 23.98778, 3.275],
							"pivot": [5.61681, 0, -11.24953],
							"rotation": [0, 60, 0],
							"uv": {
								"north": {"uv": [22, 13.5], "uv_size": [16, -7]},
								"east": {"uv": [22, 13.5], "uv_size": [16, -13.5]},
								"south": {"uv": [22, 13.5], "uv_size": [16, -7]},
								"west": {"uv": [22, 13.5], "uv_size": [16, -13.5]},
								"up": {"uv": [22, 9.5], "uv_size": [12, -9.5]},
								"down": {"uv": [22, 0], "uv_size": [12, 9.5]}
							}
						},
						{
							"origin": [-7.1, -155.6905, -7.30869],
							"size": [5, 0.93778, 1.475],
							"uv": {
								"north": {"uv": [22, 13.5], "uv_size": [16, -7]},
								"east": {"uv": [22, 13.5], "uv_size": [16, -13.5]},
								"south": {"uv": [22, 13.5], "uv_size": [16, -7]},
								"west": {"uv": [22, 13.5], "uv_size": [16, -13.5]},
								"up": {"uv": [22, 9.5], "uv_size": [12, -9.5]},
								"down": {"uv": [22, 0], "uv_size": [12, 9.5]}
							}
						},
						{
							"origin": [-6.1, -155.69051, -12.24074],
							"size": [3, 23.98778, 3.275],
							"uv": {
								"north": {"uv": [22, 13.5], "uv_size": [16, -7]},
								"east": {"uv": [22, 13.5], "uv_size": [16, -13.5]},
								"south": {"uv": [22, 13.5], "uv_size": [16, -7]},
								"west": {"uv": [22, 13.5], "uv_size": [16, -13.5]},
								"up": {"uv": [22, 9.5], "uv_size": [12, -9.5]},
								"down": {"uv": [22, 0], "uv_size": [12, 9.5]}
							}
						},
						{
							"origin": [-16.31681, -155.6905, -10.63386],
							"size": [2, 23.98778, 3.275],
							"pivot": [-8.31681, 0, 0.0088],
							"rotation": [0, -60, 0],
							"uv": {
								"north": {"uv": [22, 13.5], "uv_size": [16, -7]},
								"east": {"uv": [22, 13.5], "uv_size": [16, -13.5]},
								"south": {"uv": [22, 13.5], "uv_size": [16, -7]},
								"west": {"uv": [22, 13.5], "uv_size": [16, -13.5]},
								"up": {"uv": [22, 9.5], "uv_size": [12, -9.5]},
								"down": {"uv": [22, 0], "uv_size": [12, 9.5]}
							}
						},
						{
							"origin": [-6.1, -152.69051, -13.49074],
							"size": [3, 20.98778, 1.275],
							"uv": {
								"north": {"uv": [22, 13.5], "uv_size": [16, -7]},
								"east": {"uv": [22, 13.5], "uv_size": [16, -13.5]},
								"south": {"uv": [22, 13.5], "uv_size": [16, -7]},
								"west": {"uv": [22, 13.5], "uv_size": [16, -13.5]},
								"up": {"uv": [22, 9.5], "uv_size": [12, -9.5]},
								"down": {"uv": [22, 0], "uv_size": [12, 9.5]}
							}
						},
						{
							"origin": [-3.45, -153.39472, -17.19171],
							"size": [0.35, 2.48778, 5.825],
							"pivot": [-2.95, -144.97583, -9.75421],
							"rotation": [-15, 0, 0],
							"uv": {
								"north": {"uv": [22, 13.5], "uv_size": [16, -7]},
								"east": {"uv": [22, 13.5], "uv_size": [16, -13.5]},
								"south": {"uv": [22, 13.5], "uv_size": [16, -7]},
								"west": {"uv": [22, 13.5], "uv_size": [16, -13.5]},
								"up": {"uv": [22, 9.5], "uv_size": [12, -9.5]},
								"down": {"uv": [22, 0], "uv_size": [12, 9.5]}
							}
						},
						{
							"origin": [-6.1, -151.18289, -19.11725],
							"size": [0.35, 2.38778, 3.225],
							"uv": {
								"north": {"uv": [22, 13.5], "uv_size": [16, -7]},
								"east": {"uv": [22, 13.5], "uv_size": [16, -13.5]},
								"south": {"uv": [22, 13.5], "uv_size": [16, -7]},
								"west": {"uv": [22, 13.5], "uv_size": [16, -13.5]},
								"up": {"uv": [22, 9.5], "uv_size": [12, -9.5]},
								"down": {"uv": [22, 0], "uv_size": [12, 9.5]}
							}
						},
						{
							"origin": [-6.1, -153.39472, -13.89171],
							"size": [3, 2.48778, 2.525],
							"pivot": [-5.85, -144.97583, -9.75421],
							"rotation": [-15, 0, 0],
							"uv": {
								"north": {"uv": [22, 13.5], "uv_size": [16, -7]},
								"east": {"uv": [22, 13.5], "uv_size": [16, -13.5]},
								"south": {"uv": [22, 13.5], "uv_size": [16, -7]},
								"west": {"uv": [22, 13.5], "uv_size": [16, -13.5]},
								"up": {"uv": [22, 9.5], "uv_size": [12, -9.5]},
								"down": {"uv": [22, 0], "uv_size": [12, 9.5]}
							}
						},
						{
							"origin": [-3.45, -151.18289, -17.11725],
							"size": [0.35, 17.13778, 1.225],
							"uv": {
								"north": {"uv": [22, 13.5], "uv_size": [16, -7]},
								"east": {"uv": [22, 13.5], "uv_size": [16, -13.5]},
								"south": {"uv": [22, 13.5], "uv_size": [16, -7]},
								"west": {"uv": [22, 13.5], "uv_size": [16, -13.5]},
								"up": {"uv": [22, 9.5], "uv_size": [12, -9.5]},
								"down": {"uv": [22, 0], "uv_size": [12, 9.5]}
							}
						},
						{
							"origin": [-3.45, -149.83791, -18.082],
							"size": [0.35, 16.38778, 1.225],
							"pivot": [-2.95, -141.41902, -10.6445],
							"rotation": [-7.5, 0, 0],
							"uv": {
								"north": {"uv": [22, 13.5], "uv_size": [16, -7]},
								"east": {"uv": [22, 13.5], "uv_size": [16, -13.5]},
								"south": {"uv": [22, 13.5], "uv_size": [16, -7]},
								"west": {"uv": [22, 13.5], "uv_size": [16, -13.5]},
								"up": {"uv": [22, 9.5], "uv_size": [12, -9.5]},
								"down": {"uv": [22, 0], "uv_size": [12, 9.5]}
							}
						},
						{
							"origin": [-3.45, -148.93289, -18.11725],
							"size": [0.35, 5.88778, 2.225],
							"uv": {
								"north": {"uv": [22, 13.5], "uv_size": [16, -7]},
								"east": {"uv": [22, 13.5], "uv_size": [16, -13.5]},
								"south": {"uv": [22, 13.5], "uv_size": [16, -7]},
								"west": {"uv": [22, 13.5], "uv_size": [16, -13.5]},
								"up": {"uv": [22, 9.5], "uv_size": [12, -9.5]},
								"down": {"uv": [22, 0], "uv_size": [12, 9.5]}
							}
						},
						{
							"origin": [-6.1, -151.18289, -17.11725],
							"size": [0.35, 17.13778, 1.225],
							"uv": {
								"north": {"uv": [22, 13.5], "uv_size": [16, -7]},
								"east": {"uv": [22, 13.5], "uv_size": [16, -13.5]},
								"south": {"uv": [22, 13.5], "uv_size": [16, -7]},
								"west": {"uv": [22, 13.5], "uv_size": [16, -13.5]},
								"up": {"uv": [22, 9.5], "uv_size": [12, -9.5]},
								"down": {"uv": [22, 0], "uv_size": [12, 9.5]}
							}
						},
						{
							"origin": [-6.1, -153.39472, -17.19171],
							"size": [0.35, 2.48778, 5.825],
							"pivot": [-5.85, -144.97583, -9.75421],
							"rotation": [-15, 0, 0],
							"uv": {
								"north": {"uv": [22, 13.5], "uv_size": [16, -7]},
								"east": {"uv": [22, 13.5], "uv_size": [16, -13.5]},
								"south": {"uv": [22, 13.5], "uv_size": [16, -7]},
								"west": {"uv": [22, 13.5], "uv_size": [16, -13.5]},
								"up": {"uv": [22, 9.5], "uv_size": [12, -9.5]},
								"down": {"uv": [22, 0], "uv_size": [12, 9.5]}
							}
						},
						{
							"origin": [-3.45, -133.6853, -16.97822],
							"size": [0.35, 1.13778, 1.225],
							"uv": {
								"north": {"uv": [22, 13.5], "uv_size": [16, -7]},
								"east": {"uv": [22, 13.5], "uv_size": [16, -13.5]},
								"south": {"uv": [22, 13.5], "uv_size": [16, -7]},
								"west": {"uv": [22, 13.5], "uv_size": [16, -13.5]},
								"up": {"uv": [22, 9.5], "uv_size": [12, -9.5]},
								"down": {"uv": [22, 0], "uv_size": [12, 9.5]}
							}
						},
						{
							"origin": [-6.1, -148.93289, -18.11725],
							"size": [0.35, 5.88778, 2.225],
							"uv": {
								"north": {"uv": [22, 13.5], "uv_size": [16, -7]},
								"east": {"uv": [22, 13.5], "uv_size": [16, -13.5]},
								"south": {"uv": [22, 13.5], "uv_size": [16, -7]},
								"west": {"uv": [22, 13.5], "uv_size": [16, -13.5]},
								"up": {"uv": [22, 9.5], "uv_size": [12, -9.5]},
								"down": {"uv": [22, 0], "uv_size": [12, 9.5]}
							}
						},
						{
							"origin": [-6.1, -133.6853, -16.97822],
							"size": [0.35, 1.13778, 1.225],
							"uv": {
								"north": {"uv": [22, 13.5], "uv_size": [16, -7]},
								"east": {"uv": [22, 13.5], "uv_size": [16, -13.5]},
								"south": {"uv": [22, 13.5], "uv_size": [16, -7]},
								"west": {"uv": [22, 13.5], "uv_size": [16, -13.5]},
								"up": {"uv": [22, 9.5], "uv_size": [12, -9.5]},
								"down": {"uv": [22, 0], "uv_size": [12, 9.5]}
							}
						},
						{
							"origin": [-3.45, -151.18289, -19.11725],
							"size": [0.35, 2.38778, 3.225],
							"uv": {
								"north": {"uv": [22, 13.5], "uv_size": [16, -7]},
								"east": {"uv": [22, 13.5], "uv_size": [16, -13.5]},
								"south": {"uv": [22, 13.5], "uv_size": [16, -7]},
								"west": {"uv": [22, 13.5], "uv_size": [16, -13.5]},
								"up": {"uv": [22, 9.5], "uv_size": [12, -9.5]},
								"down": {"uv": [22, 0], "uv_size": [12, 9.5]}
							}
						},
						{
							"origin": [-6.1, -151.49472, -14.39171],
							"size": [3, 0.58778, 0.525],
							"pivot": [-5.85, -144.97583, -9.75421],
							"rotation": [-15, 0, 0],
							"uv": {
								"north": {"uv": [22, 13.5], "uv_size": [16, -7]},
								"east": {"uv": [22, 13.5], "uv_size": [16, -13.5]},
								"south": {"uv": [22, 13.5], "uv_size": [16, -7]},
								"west": {"uv": [22, 13.5], "uv_size": [16, -13.5]},
								"up": {"uv": [22, 9.5], "uv_size": [12, -9.5]},
								"down": {"uv": [22, 0], "uv_size": [12, 9.5]}
							}
						},
						{
							"origin": [-6.1, -152.01529, -15.96552],
							"size": [3, 19.58778, 0.25],
							"uv": {
								"north": {"uv": [22, 13.5], "uv_size": [16, -7]},
								"east": {"uv": [22, 13.5], "uv_size": [16, -13.5]},
								"south": {"uv": [22, 13.5], "uv_size": [16, -7]},
								"west": {"uv": [22, 13.5], "uv_size": [16, -13.5]},
								"up": {"uv": [22, 9.5], "uv_size": [12, -9.5]},
								"down": {"uv": [22, 0], "uv_size": [12, 9.5]}
							}
						},
						{
							"origin": [-6.1, -149.83791, -18.082],
							"size": [0.35, 16.38778, 1.225],
							"pivot": [-5.85, -141.41902, -10.6445],
							"rotation": [-7.5, 0, 0],
							"uv": {
								"north": {"uv": [22, 13.5], "uv_size": [16, -7]},
								"east": {"uv": [22, 13.5], "uv_size": [16, -13.5]},
								"south": {"uv": [22, 13.5], "uv_size": [16, -7]},
								"west": {"uv": [22, 13.5], "uv_size": [16, -13.5]},
								"up": {"uv": [22, 9.5], "uv_size": [12, -9.5]},
								"down": {"uv": [22, 0], "uv_size": [12, 9.5]}
							}
						},
						{
							"origin": [-6.1, -152.59472, -14.09171],
							"size": [3, 0.68778, 0.325],
							"pivot": [-5.85, -144.97583, -9.75421],
							"rotation": [-15, 0, 0],
							"uv": {
								"north": {"uv": [22, 13.5], "uv_size": [16, -7]},
								"east": {"uv": [22, 13.5], "uv_size": [16, -13.5]},
								"south": {"uv": [22, 13.5], "uv_size": [16, -7]},
								"west": {"uv": [22, 13.5], "uv_size": [16, -13.5]},
								"up": {"uv": [22, 9.5], "uv_size": [12, -9.5]},
								"down": {"uv": [22, 0], "uv_size": [12, 9.5]}
							}
						},
						{
							"origin": [-6.1, -152.01529, -15.96552],
							"size": [3, 0.93778, 0.4],
							"uv": {
								"north": {"uv": [22, 13.5], "uv_size": [16, -7]},
								"east": {"uv": [22, 13.5], "uv_size": [16, -13.5]},
								"south": {"uv": [22, 13.5], "uv_size": [16, -7]},
								"west": {"uv": [22, 13.5], "uv_size": [16, -13.5]},
								"up": {"uv": [22, 9.5], "uv_size": [12, -9.5]},
								"down": {"uv": [22, 0], "uv_size": [12, 9.5]}
							}
						},
						{
							"origin": [-6.1, -127.13117, -7.85048],
							"size": [3, 0.25, 1.025],
							"pivot": [-5.85, -139.45006, -5.21298],
							"rotation": [45, 0, 0],
							"uv": {
								"north": {"uv": [22, 13.5], "uv_size": [16, -7]},
								"east": {"uv": [22, 13.5], "uv_size": [16, -13.5]},
								"south": {"uv": [22, 13.5], "uv_size": [16, -7]},
								"west": {"uv": [22, 13.5], "uv_size": [16, -13.5]},
								"up": {"uv": [22, 9.5], "uv_size": [12, -9.5]},
								"down": {"uv": [22, 0], "uv_size": [12, 9.5]}
							}
						},
						{
							"origin": [-6.1, -131.95272, -15.24074],
							"size": [3, 0.25, 3.775],
							"uv": {
								"north": {"uv": [22, 13.5], "uv_size": [16, -7]},
								"east": {"uv": [22, 13.5], "uv_size": [16, -13.5]},
								"south": {"uv": [22, 13.5], "uv_size": [16, -7]},
								"west": {"uv": [22, 13.5], "uv_size": [16, -13.5]},
								"up": {"uv": [22, 9.5], "uv_size": [12, -9.5]},
								"down": {"uv": [22, 0], "uv_size": [12, 9.5]}
							}
						},
						{
							"origin": [-5.9, -138.34824, -10.49198],
							"size": [2.5, 53.4, 2.5],
							"uv": {
								"north": {"uv": [48, 4.80769], "uv_size": [5.64706, 1.69231]},
								"east": {"uv": [48, 4.80769], "uv_size": [5.64706, -3.80769]},
								"south": {"uv": [48, 4.80769], "uv_size": [5.64706, 1.69231]},
								"west": {"uv": [48, 4.80769], "uv_size": [5.64706, -3.80769]},
								"up": {"uv": [48, 1.42308], "uv_size": [4.23529, -0.42308]},
								"down": {"uv": [48, 1], "uv_size": [4.23529, 0.42308]}
							}
						},
						{
							"origin": [-6.1, -102.34824, -10.69198],
							"size": [2.9, 2.4, 2.9],
							"uv": {
								"north": {"uv": [48, 4.80769], "uv_size": [5.64706, 1.69231]},
								"east": {"uv": [48, 4.80769], "uv_size": [5.64706, -3.80769]},
								"south": {"uv": [48, 4.80769], "uv_size": [5.64706, 1.69231]},
								"west": {"uv": [48, 4.80769], "uv_size": [5.64706, -3.80769]},
								"up": {"uv": [48, 1.42308], "uv_size": [4.23529, -0.42308]},
								"down": {"uv": [48, 1], "uv_size": [4.23529, 0.42308]}
							}
						},
						{
							"origin": [-7.4, -140.85291, -5.61823],
							"size": [5.6, 1.25, 1.25],
							"uv": {
								"north": {"uv": [43, 10], "uv_size": [16, -3.5]},
								"east": {"uv": [43, 10], "uv_size": [16, -10]},
								"south": {"uv": [43, 10], "uv_size": [16, -3.5]},
								"west": {"uv": [43, 10], "uv_size": [16, -10]},
								"up": {"uv": [43, 6], "uv_size": [12, -6]},
								"down": {"uv": [43, 0], "uv_size": [12, 6]}
							}
						},
						{
							"origin": [-5.85, -102.09824, -7.79198],
							"size": [2.4, 1.9, 3],
							"uv": {
								"north": {"uv": [48, 4.80769], "uv_size": [5.64706, 1.69231]},
								"east": {"uv": [48, 4.80769], "uv_size": [5.64706, -3.80769]},
								"south": {"uv": [48, 4.80769], "uv_size": [5.64706, 1.69231]},
								"west": {"uv": [48, 4.80769], "uv_size": [5.64706, -3.80769]},
								"up": {"uv": [48, 1.42308], "uv_size": [4.23529, -0.42308]},
								"down": {"uv": [48, 1], "uv_size": [4.23529, 0.42308]}
							}
						},
						{
							"origin": [-7.4, -144.10291, -8.16823],
							"size": [5.6, 2.25, 0.75],
							"pivot": [-4.6, -142.10291, -7.79323],
							"rotation": [90, 0, 0],
							"uv": {
								"north": {"uv": [43, 10], "uv_size": [16, -3.5]},
								"east": {"uv": [43, 10], "uv_size": [16, -10]},
								"south": {"uv": [43, 10], "uv_size": [16, -3.5]},
								"west": {"uv": [43, 10], "uv_size": [16, -10]},
								"up": {"uv": [43, 6], "uv_size": [12, -6]},
								"down": {"uv": [43, 0], "uv_size": [12, 6]}
							}
						},
						{
							"origin": [-5.85, -102.09824, -6.29198],
							"size": [2.4, 3.9, 1.5],
							"uv": {
								"north": {"uv": [48, 4.80769], "uv_size": [5.64706, 1.69231]},
								"east": {"uv": [48, 4.80769], "uv_size": [5.64706, -3.80769]},
								"south": {"uv": [48, 4.80769], "uv_size": [5.64706, 1.69231]},
								"west": {"uv": [48, 4.80769], "uv_size": [5.64706, -3.80769]},
								"up": {"uv": [48, 1.42308], "uv_size": [4.23529, -0.42308]},
								"down": {"uv": [48, 1], "uv_size": [4.23529, 0.42308]}
							}
						},
						{
							"origin": [-7.4, -141.85291, -8.41823],
							"size": [5.6, 1.25, 1.25],
							"pivot": [-4.6, -142.10291, -7.79323],
							"rotation": [90, 0, 0],
							"uv": {
								"north": {"uv": [43, 10], "uv_size": [16, -3.5]},
								"east": {"uv": [43, 10], "uv_size": [16, -10]},
								"south": {"uv": [43, 10], "uv_size": [16, -3.5]},
								"west": {"uv": [43, 10], "uv_size": [16, -10]},
								"up": {"uv": [43, 6], "uv_size": [12, -6]},
								"down": {"uv": [43, 0], "uv_size": [12, 6]}
							}
						},
						{
							"origin": [-7.4, -143.10291, -5.36823],
							"size": [5.6, 2.25, 0.75],
							"uv": {
								"north": {"uv": [43, 10], "uv_size": [16, -3.5]},
								"east": {"uv": [43, 10], "uv_size": [16, -10]},
								"south": {"uv": [43, 10], "uv_size": [16, -3.5]},
								"west": {"uv": [43, 10], "uv_size": [16, -10]},
								"up": {"uv": [43, 6], "uv_size": [12, -6]},
								"down": {"uv": [43, 0], "uv_size": [12, 6]}
							}
						},
						{
							"origin": [-6.1, -88.84824, -10.69198],
							"size": [2.9, 4.4, 2.9],
							"uv": {
								"north": {"uv": [48, 4.80769], "uv_size": [5.64706, 1.69231]},
								"east": {"uv": [48, 4.80769], "uv_size": [5.64706, -3.80769]},
								"south": {"uv": [48, 4.80769], "uv_size": [5.64706, 1.69231]},
								"west": {"uv": [48, 4.80769], "uv_size": [5.64706, -3.80769]},
								"up": {"uv": [48, 1.42308], "uv_size": [4.23529, -0.42308]},
								"down": {"uv": [48, 1], "uv_size": [4.23529, 0.42308]}
							}
						},
						{
							"origin": [-6.7, -139.50164, -2.75058],
							"size": [4.2, 6.5, 6],
							"pivot": [-4.6, -137.75164, 1.24942],
							"rotation": [12.5, 0, 0],
							"uv": {
								"north": {"uv": [44, 1], "uv_size": [15, 13]},
								"east": {"uv": [44, 1], "uv_size": [15, 13]},
								"south": {"uv": [44, 1], "uv_size": [15, 13]},
								"west": {"uv": [44, 1], "uv_size": [15, 13]},
								"up": {"uv": [44, 1], "uv_size": [15, 13]},
								"down": {"uv": [59, 14], "uv_size": [-15, -8.5]}
							}
						},
						{
							"origin": [-6.7, -137.62975, 2.60661],
							"size": [4.2, 6.5, 5],
							"pivot": [-4.6, -135.87975, 6.60661],
							"rotation": [22.5, 0, 0],
							"uv": {
								"north": {"uv": [44, 1], "uv_size": [15, 13]},
								"east": {"uv": [44, 1], "uv_size": [15, 13]},
								"south": {"uv": [44, 1], "uv_size": [15, 13]},
								"west": {"uv": [44, 1], "uv_size": [15, 13]},
								"up": {"uv": [44, 1], "uv_size": [15, 13]},
								"down": {"uv": [59, 14], "uv_size": [-15, -8.5]}
							}
						},
						{
							"origin": [-6.7, -135.34831, 6.78928],
							"size": [4.2, 6.5, 5],
							"pivot": [-4.6, -133.59831, 10.78928],
							"rotation": [30, 0, 0],
							"uv": {
								"north": {"uv": [44, 1], "uv_size": [15, 13]},
								"east": {"uv": [44, 1], "uv_size": [15, 13]},
								"south": {"uv": [44, 1], "uv_size": [15, 13]},
								"west": {"uv": [44, 1], "uv_size": [15, 13]},
								"up": {"uv": [44, 1], "uv_size": [15, 13]},
								"down": {"uv": [59, 14], "uv_size": [-15, -8.5]}
							}
						},
						{
							"origin": [-6.1, -82.04824, -10.69198],
							"size": [2.9, 0.75, 2.9],
							"uv": {
								"north": {"uv": [48, 4.80769], "uv_size": [5.64706, 1.69231]},
								"east": {"uv": [48, 4.80769], "uv_size": [5.64706, -3.80769]},
								"south": {"uv": [48, 4.80769], "uv_size": [5.64706, 1.69231]},
								"west": {"uv": [48, 4.80769], "uv_size": [5.64706, -3.80769]},
								"up": {"uv": [48, 1.42308], "uv_size": [4.23529, -0.42308]},
								"down": {"uv": [48, 1], "uv_size": [4.23529, 0.42308]}
							}
						},
						{
							"origin": [-6.1, -84.94824, -8.19198],
							"size": [2.9, 3, 0.4],
							"uv": {
								"north": {"uv": [53.35294, 2], "uv_size": [5.64706, 5.5]},
								"east": {"uv": [44, 15.5], "uv_size": [16, -13.5]},
								"south": {"uv": [48, 4.80769], "uv_size": [5.64706, 1.69231]},
								"west": {"uv": [48, 4.80769], "uv_size": [5.64706, -3.80769]},
								"up": {"uv": [48, 1.42308], "uv_size": [4.23529, -0.42308]},
								"down": {"uv": [48, 1], "uv_size": [4.23529, 0.42308]}
							}
						},
						{
							"origin": [-6.1, -84.94824, -10.69198],
							"size": [2.9, 3, 0.4],
							"uv": {
								"north": {"uv": [48, 4.80769], "uv_size": [5.64706, 1.69231]},
								"east": {"uv": [48, 4.80769], "uv_size": [5.64706, -3.80769]},
								"south": {"uv": [48, 4.80769], "uv_size": [5.64706, 1.69231]},
								"west": {"uv": [48, 4.80769], "uv_size": [5.64706, -3.80769]},
								"up": {"uv": [48, 1.42308], "uv_size": [4.23529, -0.42308]},
								"down": {"uv": [48, 1], "uv_size": [4.23529, 0.42308]}
							}
						}
					]
				},
				{
					"name": "bone10",
					"parent": "bone9",
					"pivot": [-0.2, 0, 0],
					"cubes": [
						{
							"origin": [-16.31681, -179.9405, -10.63386],
							"size": [2, 24.25, 3.275],
							"pivot": [-8.31681, 0, 0.0088],
							"rotation": [0, -60, 0],
							"uv": {
								"north": {"uv": [46, 6.5], "uv_size": [13, -2]},
								"east": {"uv": [46, 2.5], "uv_size": [13, -0.5]},
								"south": {"uv": [46, 6.5], "uv_size": [13, -2]},
								"west": {"uv": [46, 2.5], "uv_size": [13, -0.5]},
								"up": {"uv": [46, 2], "uv_size": [9, 0]},
								"down": {"uv": [46, 2], "uv_size": [9, 0]}
							}
						},
						{
							"origin": [-6.1, -179.94051, -12.24074],
							"size": [3, 24.25, 3.275],
							"uv": {
								"north": {"uv": [46, 6.5], "uv_size": [13, -2]},
								"east": {"uv": [46, 2.5], "uv_size": [13, -0.5]},
								"south": {"uv": [46, 6.5], "uv_size": [13, -2]},
								"west": {"uv": [46, 2.5], "uv_size": [13, -0.5]},
								"up": {"uv": [46, 2], "uv_size": [9, 0]},
								"down": {"uv": [46, 2], "uv_size": [9, 0]}
							}
						},
						{
							"origin": [-1.38319, -179.9405, -21.89219],
							"size": [2, 24.25, 3.275],
							"pivot": [5.61681, 0, -11.24953],
							"rotation": [0, 60, 0],
							"uv": {
								"north": {"uv": [46, 6.5], "uv_size": [13, -2]},
								"east": {"uv": [46, 2.5], "uv_size": [13, -0.5]},
								"south": {"uv": [46, 6.5], "uv_size": [13, -2]},
								"west": {"uv": [46, 2.5], "uv_size": [13, -0.5]},
								"up": {"uv": [46, 2], "uv_size": [9, 0]},
								"down": {"uv": [46, 2], "uv_size": [9, 0]}
							}
						},
						{
							"origin": [-7.1, -179.9405, -10.50869],
							"size": [5, 24.25, 3.275],
							"uv": {
								"north": {"uv": [46, 6.5], "uv_size": [13, -2]},
								"east": {"uv": [46, 2.5], "uv_size": [13, -0.5]},
								"south": {"uv": [46, 6.5], "uv_size": [13, -2]},
								"west": {"uv": [46, 2.5], "uv_size": [13, -0.5]},
								"up": {"uv": [46, 2], "uv_size": [9, 0]},
								"down": {"uv": [46, 2], "uv_size": [9, 0]}
							}
						},
						{
							"origin": [-7.1, -178.6905, -7.30869],
							"size": [5, 23, 1.475],
							"uv": {
								"north": {"uv": [46, 6.5], "uv_size": [13, -2]},
								"east": {"uv": [46, 2], "uv_size": [10, 0]},
								"south": {"uv": [46, 6.5], "uv_size": [13, -2]},
								"west": {"uv": [46, 2.5], "uv_size": [13, -0.5]},
								"up": {"uv": [46, 2], "uv_size": [9, 0]},
								"down": {"uv": [46, 2], "uv_size": [9, 0]}
							}
						},
						{
							"origin": [-7.1, -179.9405, -7.30869],
							"size": [5, 1.25, 10.475],
							"uv": {
								"north": {"uv": [46, 6.5], "uv_size": [13, -2]},
								"east": {"uv": [46, 2], "uv_size": [10, 0]},
								"south": {"uv": [46, 6.5], "uv_size": [13, -2]},
								"west": {"uv": [46, 2.5], "uv_size": [13, -0.5]},
								"up": {"uv": [46, 2], "uv_size": [9, 0]},
								"down": {"uv": [46, 2], "uv_size": [9, 0]}
							}
						},
						{
							"origin": [-7.1, -174.1552, -12.69081],
							"size": [5, 0, 18.475],
							"pivot": [-4.6, -174.1552, 0.54669],
							"rotation": [-60, 0, 0],
							"uv": {
								"north": {"uv": [46, 6.5], "uv_size": [13, -2]},
								"east": {"uv": [46, 2], "uv_size": [10, 0]},
								"south": {"uv": [46, 6.5], "uv_size": [13, -2]},
								"west": {"uv": [46, 2.5], "uv_size": [13, -0.5]},
								"up": {"uv": [46, 2], "uv_size": [9, 0]},
								"down": {"uv": [46, 2], "uv_size": [9, 0]}
							}
						},
						{
							"origin": [-7.1, -176.4052, -12.69081],
							"size": [5, 2.25, 18.475],
							"pivot": [-4.6, -174.1552, 0.54669],
							"rotation": [-60, 0, 0],
							"uv": {
								"north": {"uv": [46, 6.5], "uv_size": [13, -2]},
								"east": {"uv": [46, 2], "uv_size": [10, 0]},
								"south": {"uv": [46, 6.5], "uv_size": [13, -2]},
								"west": {"uv": [46, 2.5], "uv_size": [13, -0.5]},
								"up": {"uv": [46, 2], "uv_size": [9, 0]},
								"down": {"uv": [46, 2], "uv_size": [9, 0]}
							}
						},
						{
							"origin": [-7.1, -180.6552, -5.94081],
							"size": [5, 2, 9.225],
							"pivot": [-4.6, -174.1552, 0.54669],
							"rotation": [-60, 0, 0],
							"uv": {
								"north": {"uv": [46, 6.5], "uv_size": [13, -2]},
								"east": {"uv": [46, 2], "uv_size": [10, 0]},
								"south": {"uv": [46, 6.5], "uv_size": [13, -2]},
								"west": {"uv": [46, 2.5], "uv_size": [13, -0.5]},
								"up": {"uv": [46, 2], "uv_size": [9, 0]},
								"down": {"uv": [46, 2], "uv_size": [9, 0]}
							}
						},
						{
							"origin": [-7.1, -178.6552, -8.69081],
							"size": [5, 2.25, 13.225],
							"pivot": [-4.6, -174.1552, 0.54669],
							"rotation": [-60, 0, 0],
							"uv": {
								"north": {"uv": [46, 6.5], "uv_size": [13, -2]},
								"east": {"uv": [46, 2], "uv_size": [10, 0]},
								"south": {"uv": [46, 6.5], "uv_size": [13, -2]},
								"west": {"uv": [46, 2.5], "uv_size": [13, -0.5]},
								"up": {"uv": [46, 2], "uv_size": [9, 0]},
								"down": {"uv": [46, 2], "uv_size": [9, 0]}
							}
						},
						{
							"origin": [-7.1, -182.1552, -5.69081],
							"size": [5, 2, 8.225],
							"pivot": [-4.6, -174.1552, 0.54669],
							"rotation": [-60, 0, 0],
							"uv": {
								"north": {"uv": [46, 6.5], "uv_size": [13, -2]},
								"east": {"uv": [46, 2], "uv_size": [10, 0]},
								"south": {"uv": [46, 6.5], "uv_size": [13, -2]},
								"west": {"uv": [46, 2.5], "uv_size": [13, -0.5]},
								"up": {"uv": [46, 2], "uv_size": [9, 0]},
								"down": {"uv": [46, 2], "uv_size": [9, 0]}
							}
						}
					]
				},
				{
					"name": "bone12",
					"parent": "bone9",
					"pivot": [-5.85, -144.4964, -10.57802],
					"cubes": [
						{
							"origin": [-5.35, -151.01529, -18.21552],
							"size": [1.5, 1, 0.15],
							"uv": {
								"north": {"uv": [44, 13.5], "uv_size": [16, -7]},
								"east": {"uv": [44, 13.5], "uv_size": [16, -13.5]},
								"south": {"uv": [44, 13.5], "uv_size": [16, -7]},
								"west": {"uv": [44, 13.5], "uv_size": [16, -13.5]},
								"up": {"uv": [44, 9.5], "uv_size": [12, -9.5]},
								"down": {"uv": [44, 0], "uv_size": [12, 9.5]}
							}
						},
						{
							"origin": [-4, -151.01529, -18.21552],
							"size": [0.15, 1, 1.5],
							"uv": {
								"north": {"uv": [44, 13.5], "uv_size": [16, -7]},
								"east": {"uv": [44, 13.5], "uv_size": [16, -13.5]},
								"south": {"uv": [44, 13.5], "uv_size": [16, -7]},
								"west": {"uv": [44, 13.5], "uv_size": [16, -13.5]},
								"up": {"uv": [44, 9.5], "uv_size": [12, -9.5]},
								"down": {"uv": [44, 0], "uv_size": [12, 9.5]}
							}
						},
						{
							"origin": [-5.35, -151.01529, -16.86552],
							"size": [1.5, 1, 0.15],
							"uv": {
								"north": {"uv": [44, 13.5], "uv_size": [16, -7]},
								"east": {"uv": [44, 13.5], "uv_size": [16, -13.5]},
								"south": {"uv": [44, 13.5], "uv_size": [16, -7]},
								"west": {"uv": [44, 13.5], "uv_size": [16, -13.5]},
								"up": {"uv": [44, 9.5], "uv_size": [12, -9.5]},
								"down": {"uv": [44, 0], "uv_size": [12, 9.5]}
							}
						},
						{
							"origin": [-5.35, -151.01529, -18.21552],
							"size": [0.15, 1, 1.5],
							"uv": {
								"north": {"uv": [44, 13.5], "uv_size": [16, -7]},
								"east": {"uv": [44, 13.5], "uv_size": [16, -13.5]},
								"south": {"uv": [44, 13.5], "uv_size": [16, -7]},
								"west": {"uv": [44, 13.5], "uv_size": [16, -13.5]},
								"up": {"uv": [44, 9.5], "uv_size": [12, -9.5]},
								"down": {"uv": [44, 0], "uv_size": [12, 9.5]}
							}
						},
						{
							"origin": [-5.1, -151.01529, -16.71552],
							"size": [1, 1, 1.25],
							"uv": {
								"north": {"uv": [44, 13.5], "uv_size": [16, -7]},
								"east": {"uv": [44, 13.5], "uv_size": [16, -13.5]},
								"south": {"uv": [44, 13.5], "uv_size": [16, -7]},
								"west": {"uv": [44, 13.5], "uv_size": [16, -13.5]},
								"up": {"uv": [44, 9.5], "uv_size": [12, -9.5]},
								"down": {"uv": [44, 0], "uv_size": [12, 9.5]}
							}
						}
					]
				},
				{
					"name": "bone17",
					"parent": "bone9",
					"pivot": [-4.6, -141.49831, 10.78928],
					"cubes": [
						{
							"origin": [-5.5, -102.89824, -15.94198],
							"size": [1.6, 1.9, 1.95],
							"uv": {
								"north": {"uv": [48, 4.80769], "uv_size": [5.64706, 1.69231]},
								"east": {"uv": [48, 4.80769], "uv_size": [5.64706, -3.80769]},
								"south": {"uv": [48, 4.80769], "uv_size": [5.64706, 1.69231]},
								"west": {"uv": [48, 4.80769], "uv_size": [5.64706, -3.80769]},
								"up": {"uv": [48, 1.42308], "uv_size": [4.23529, -0.42308]},
								"down": {"uv": [48, 1], "uv_size": [4.23529, 0.42308]}
							}
						},
						{
							"origin": [-5.5, -101.24824, -15.94198],
							"size": [1.5, 0.5, 5.95],
							"uv": {
								"north": {"uv": [48, 4.80769], "uv_size": [5.64706, 1.69231]},
								"east": {"uv": [44, 15.5], "uv_size": [16, -13.5]},
								"south": {"uv": [48, 4.80769], "uv_size": [5.64706, 1.69231]},
								"west": {"uv": [48, 4.80769], "uv_size": [5.64706, -3.80769]},
								"up": {"uv": [53.35294, 2], "uv_size": [4.23529, 0]},
								"down": {"uv": [48, 1], "uv_size": [4.23529, 0.42308]}
							}
						},
						{
							"origin": [-4.75, -102.64824, -17.39198],
							"size": [0.1, 0.9, 2.45],
							"uv": {
								"north": {"uv": [48, 4.80769], "uv_size": [5.64706, 1.69231]},
								"east": {"uv": [48, 4.80769], "uv_size": [5.64706, -3.80769]},
								"south": {"uv": [48, 4.80769], "uv_size": [5.64706, 1.69231]},
								"west": {"uv": [48, 4.80769], "uv_size": [5.64706, -3.80769]},
								"up": {"uv": [48, 1.42308], "uv_size": [4.23529, -0.42308]},
								"down": {"uv": [48, 1], "uv_size": [4.23529, 0.42308]}
							}
						},
						{
							"origin": [-5, -106.24824, -12.44198],
							"size": [0.5, 5.5, 1.45],
							"uv": {
								"north": {"uv": [48, 4.80769], "uv_size": [5.64706, 1.69231]},
								"east": {"uv": [48, 4.80769], "uv_size": [5.64706, -3.80769]},
								"south": {"uv": [48, 4.80769], "uv_size": [5.64706, 1.69231]},
								"west": {"uv": [48, 4.80769], "uv_size": [5.64706, -3.80769]},
								"up": {"uv": [48, 1.42308], "uv_size": [4.23529, -0.42308]},
								"down": {"uv": [48, 1], "uv_size": [4.23529, 0.42308]}
							}
						},
						{
							"origin": [-5.5, -102.89824, -17.12499],
							"size": [0.2, 2.15, 1.25],
							"uv": {
								"north": {"uv": [48, 4.80769], "uv_size": [5.64706, 1.69231]},
								"east": {"uv": [48, 4.80769], "uv_size": [5.64706, -3.80769]},
								"south": {"uv": [48, 4.80769], "uv_size": [5.64706, 1.69231]},
								"west": {"uv": [48, 4.80769], "uv_size": [5.64706, -3.80769]},
								"up": {"uv": [48, 1.42308], "uv_size": [4.23529, -0.42308]},
								"down": {"uv": [48, 1], "uv_size": [4.23529, 0.42308]}
							}
						},
						{
							"origin": [-4.48839, -102.89824, -17.40752],
							"size": [0.2, 2.15, 0.5],
							"pivot": [-3.88839, -100.57324, -16.2915],
							"rotation": [0, -30, 0],
							"uv": {
								"north": {"uv": [48, 4.80769], "uv_size": [5.64706, 1.69231]},
								"east": {"uv": [48, 4.80769], "uv_size": [5.64706, -3.80769]},
								"south": {"uv": [48, 4.80769], "uv_size": [5.64706, 1.69231]},
								"west": {"uv": [48, 4.80769], "uv_size": [5.64706, -3.80769]},
								"up": {"uv": [48, 1.42308], "uv_size": [4.23529, -0.42308]},
								"down": {"uv": [48, 1], "uv_size": [4.23529, 0.42308]}
							}
						},
						{
							"origin": [-4.75, -101.97546, -17.3311],
							"size": [0.1, 0.9, 1.95],
							"pivot": [-4.7, -101.52546, -16.1061],
							"rotation": [30, 0, 0],
							"uv": {
								"north": {"uv": [48, 4.80769], "uv_size": [5.64706, 1.69231]},
								"east": {"uv": [48, 4.80769], "uv_size": [5.64706, -3.80769]},
								"south": {"uv": [48, 4.80769], "uv_size": [5.64706, 1.69231]},
								"west": {"uv": [48, 4.80769], "uv_size": [5.64706, -3.80769]},
								"up": {"uv": [48, 1.42308], "uv_size": [4.23529, -0.42308]},
								"down": {"uv": [48, 1], "uv_size": [4.23529, 0.42308]}
							}
						},
						{
							"origin": [-4.1, -102.89824, -17.12499],
							"size": [0.2, 2.15, 1.25],
							"uv": {
								"north": {"uv": [48, 4.80769], "uv_size": [5.64706, 1.69231]},
								"east": {"uv": [48, 4.80769], "uv_size": [5.64706, -3.80769]},
								"south": {"uv": [48, 4.80769], "uv_size": [5.64706, 1.69231]},
								"west": {"uv": [48, 4.80769], "uv_size": [5.64706, -3.80769]},
								"up": {"uv": [48, 1.42308], "uv_size": [4.23529, -0.42308]},
								"down": {"uv": [48, 1], "uv_size": [4.23529, 0.42308]}
							}
						},
						{
							"origin": [-5.6741, -102.89824, -17.52475],
							"size": [0.2, 2.15, 0.5],
							"pivot": [-5.5741, -102.94824, -17.39975],
							"rotation": [0, 30, 0],
							"uv": {
								"north": {"uv": [48, 4.80769], "uv_size": [5.64706, 1.69231]},
								"east": {"uv": [48, 4.80769], "uv_size": [5.64706, -3.80769]},
								"south": {"uv": [48, 4.80769], "uv_size": [5.64706, 1.69231]},
								"west": {"uv": [48, 4.80769], "uv_size": [5.64706, -3.80769]},
								"up": {"uv": [48, 1.42308], "uv_size": [4.23529, -0.42308]},
								"down": {"uv": [48, 1], "uv_size": [4.23529, 0.42308]}
							}
						},
						{
							"origin": [-5.5, -103.8797, -15.03197],
							"size": [1.6, 1.25, 7.05],
							"pivot": [-4.75, -102.21549, -14.12118],
							"rotation": [-45, 0, 0],
							"uv": {
								"north": {"uv": [48, 4.80769], "uv_size": [5.64706, 1.69231]},
								"east": {"uv": [48, 4.80769], "uv_size": [5.64706, -3.80769]},
								"south": {"uv": [48, 4.80769], "uv_size": [5.64706, 1.69231]},
								"west": {"uv": [48, 4.80769], "uv_size": [5.64706, -3.80769]},
								"up": {"uv": [48, 1.42308], "uv_size": [4.23529, -0.42308]},
								"down": {"uv": [48, 1], "uv_size": [4.23529, 0.42308]}
							}
						}
					]
				},
				{
					"name": "bone20",
					"parent": "bone9",
					"pivot": [-0.15174, 9.5, -1.34186]
				},
				{
					"name": "bone21",
					"parent": "bone9",
					"pivot": [4.59826, 9.5, -1.34186]
				},
				{
					"name": "bone23",
					"parent": "bone9",
					"pivot": [-0.1, -4, -1]
				},
				{
					"name": "bone22",
					"parent": "bone9",
					"pivot": [-2.22674, -115.08991, -0.08384],
					"rotation": [0, 30, 0]
				},
				{
					"name": "bone19",
					"parent": "bone9",
					"pivot": [-5.37452, -123.54824, -15.96746]
				},
				{
					"name": "bone5",
					"parent": "bone9",
					"pivot": [-0.1, 15.20449, -2.29381]
				},
				{
					"name": "bone4",
					"parent": "bone5",
					"pivot": [-4.57308, -116.65272, -9.49314]
				},
				{
					"name": "bone3",
					"parent": "bone5",
					"pivot": [-4.57308, -104.65272, -12.29314],
					"rotation": [180, 0, 0]
				},
				{
					"name": "bone2",
					"parent": "bone9",
					"pivot": [-4.69138, -139.39824, -11.61539]
				},
				{
					"name": "bone30",
					"parent": "bone2",
					"pivot": [-0.1, -7, -1]
				},
				{
					"name": "bone31",
					"parent": "bone2",
					"pivot": [-0.1, -7, -1]
				},
				{
					"name": "bone29",
					"parent": "bone2",
					"pivot": [-4.58682, -153.92324, -16.24735],
					"rotation": [30, 0, 0]
				},
				{
					"name": "bone28",
					"parent": "bone2",
					"pivot": [-4.58682, -148.49824, -16.24735],
					"rotation": [30, 0, 0]
				},
				{
					"name": "bone27",
					"parent": "bone2",
					"pivot": [-4.58682, -148.92324, -16.24735],
					"rotation": [30, 0, 0]
				},
				{
					"name": "bone26",
					"parent": "bone2",
					"pivot": [-0.1, 0, -1]
				},
				{
					"name": "bone25",
					"parent": "bone2",
					"pivot": [-0.1, 0, -1]
				},
				{
					"name": "bone",
					"parent": "bone9",
					"pivot": [-4.57308, -122.65272, -8.99314],
					"rotation": [5, 0, 0]
				},
				{
					"name": "guncube5",
					"parent": "guncube",
					"pivot": [-5.12983, -143.99071, 7.82014],
					"rotation": [-25, 0, 0],
					"cubes": [
						{
							"origin": [-7.45, -155.50164, 2.24942],
							"size": [5.7, 4.25, 8],
							"pivot": [-4.6, -153.75164, 6.24942],
							"rotation": [-5, 0, 0],
							"uv": {
								"north": {"uv": [44, 1], "uv_size": [15, 13]},
								"east": {"uv": [45, 2], "uv_size": [15, 13]},
								"south": {"uv": [44, 1], "uv_size": [15, 13]},
								"west": {"uv": [44, 1], "uv_size": [15, 13]},
								"up": {"uv": [44, 1], "uv_size": [15, 13]},
								"down": {"uv": [59, 14], "uv_size": [-15, -8.5]}
							}
						}
					]
				},
				{
					"name": "bone6",
					"parent": "guncube",
					"pivot": [-6.1, -34, -52],
					"rotation": [25, 0, 0]
				},
				{
					"name": "bone7",
					"parent": "bone6",
					"pivot": [-0.1, -20, 22]
				},
				{
					"name": "bone14",
					"parent": "guncube",
					"pivot": [-1.1, -1, 0]
				},
				{
					"name": "bone8",
					"parent": "bone14",
					"pivot": [-0.1, -154, -2],
					"rotation": [30, 0, 0]
				},
				{
					"name": "leftArmA",
					"parent": "root",
					"pivot": [5, 22, 0]
				},
				{
					"name": "leftArm",
					"parent": "leftArmA",
					"pivot": [5, 22, 0]
				}
			]
		}
	]
}