{"format_version":"1.12.0","minecraft:geometry":[{"description":{"identifier":"geometry.arr","texture_width":64,"texture_height":64,"visible_bounds_width":5,"visible_bounds_height":2.5,"visible_bounds_offset":[0,0.75,0]},"bones":[{"name":"bb_main","pivot":[0,0,0],"cubes":[{"origin":[-2,2,-4],"size":[4,7,6],"uv":[0,0]},{"origin":[-10,3,-3],"size":[20,2,4],"uv":[0,0]}]},{"name":"dulo","pivot":[1,6,-3],"rotation":[90,0,0]},{"name":"rotator","parent":"dulo","pivot":[1,6,1]},{"name":"rotate","parent":"rotator","pivot":[1,6,1],"rotation":[0,30,0],"cubes":[{"origin":[1.2866,2.8,-0.99641],"size":[1,23,0.5],"uv":[62,0]}]},{"name":"rotate3","parent":"rotator","pivot":[2,6,1],"rotation":[0,60,0],"cubes":[{"origin":[3.36244,2.8,-1.01865],"size":[1,23,0.5],"uv":[62,0]}]},{"name":"rotate2","parent":"rotator","pivot":[4,6,1],"rotation":[0,90,0],"cubes":[{"origin":[6.80526,2.8,-1.63397],"size":[1,23,0.5],"uv":[62,0]}]},{"name":"rotate4","parent":"rotator","pivot":[7,6,1],"rotation":[0,120,0],"cubes":[{"origin":[12.86244,2.8,-2.04352],"size":[1,23,0.5],"uv":[62,0]}]},{"name":"rotate9","parent":"rotator","pivot":[7,6,1],"rotation":[0,150,0],"cubes":[{"origin":[14.21481,2.8,1.72846],"size":[1,23,0.5],"uv":[62,0]}]},{"name":"rotate10","parent":"rotator","pivot":[7,6,1],"rotation":[0,180,0],"cubes":[{"origin":[13.5,2.8,5.67128],"size":[1,23,0.5],"uv":[62,0]}]},{"name":"rotator2","parent":"dulo","pivot":[-1,6,-4],"rotation":[0,180,0]},{"name":"rotate12","parent":"rotator2","pivot":[0,6,-4],"rotation":[0,30,0],"cubes":[{"origin":[-1.38468,2.8,-5.10167],"size":[1,23,0.5],"uv":[62,0]}]},{"name":"rotate13","parent":"rotator2","pivot":[2,6,-4],"rotation":[0,60,0],"cubes":[{"origin":[0.96769,2.8,-6.94545],"size":[1,23,0.5],"uv":[62,0]}]},{"name":"rotate14","parent":"rotator2","pivot":[5,6,-4],"rotation":[0,90,0],"cubes":[{"origin":[6.19474,2.8,-9.63397],"size":[1,23,0.5],"uv":[62,0]}]},{"name":"rotate15","parent":"rotator2","pivot":[5,6,-4],"rotation":[0,120,0],"cubes":[{"origin":[9.46769,2.8,-7.84878],"size":[1,23,0.5],"uv":[62,0]}]},{"name":"rotate16","parent":"rotator2","pivot":[5,6,-4],"rotation":[0,150,0],"cubes":[{"origin":[11.40955,2.8,-4.66628],"size":[1,23,0.5],"uv":[62,0]}]},{"name":"rotate17","parent":"rotator2","pivot":[5,6,-4],"rotation":[0,180,0],"cubes":[{"origin":[11.5,2.8,-0.93923],"size":[1,23,0.5],"uv":[62,0]}]},{"name":"bone","pivot":[0,0,0],"rotation":[-15,0,0],"cubes":[{"origin":[-9,-2,-8],"size":[18,5,1],"uv":[0,0]},{"origin":[-9,8,-8],"size":[18,6,1],"uv":[0,0]},{"origin":[3,3,-8],"size":[6,5,1],"uv":[0,0]},{"origin":[-9,3,-8],"size":[6,5,1],"uv":[0,0]}]},{"name":"bone2","parent":"bone","pivot":[0,0,0]},{"name":"dulo3","parent":"bone","pivot":[1,2,13],"rotation":[-90,0,0]},{"name":"rotator5","parent":"dulo3","pivot":[1,2,17]},{"name":"rotate25","parent":"rotator5","pivot":[1,2,17],"rotation":[0,30,0],"cubes":[{"origin":[3.7866,-13.2,10.17346],"size":[1,32,0],"uv":[62,0]}]},{"name":"rotate26","parent":"rotator5","pivot":[2,2,17],"rotation":[0,60,0]},{"name":"rotate27","parent":"rotator5","pivot":[4,2,17],"rotation":[0,90,0],"cubes":[{"origin":[11.80526,-13.2,13.86603],"size":[1,32,0],"uv":[62,0]}]},{"name":"rotate28","parent":"rotator5","pivot":[7,2,17],"rotation":[0,120,0]},{"name":"rotate29","parent":"rotator5","pivot":[7,2,17],"rotation":[0,150,0],"cubes":[{"origin":[16.71481,-13.2,21.55859],"size":[1,32,0],"uv":[62,0]}]},{"name":"rotate30","parent":"rotator5","pivot":[7,2,17],"rotation":[0,180,0]},{"name":"rotator6","parent":"dulo3","pivot":[-1,2,12],"rotation":[0,180,0]},{"name":"rotate31","parent":"rotator6","pivot":[0,2,12],"rotation":[0,30,0],"cubes":[{"origin":[-3.88468,-13.2,14.72846],"size":[1,32,0],"uv":[62,0]}]},{"name":"rotate32","parent":"rotator6","pivot":[2,2,12],"rotation":[0,60,0]},{"name":"rotate33","parent":"rotator6","pivot":[5,2,12],"rotation":[0,90,0],"cubes":[{"origin":[1.19474,-13.2,5.86603],"size":[1,32,0],"uv":[62,0]}]},{"name":"rotate34","parent":"rotator6","pivot":[5,2,12],"rotation":[0,120,0]},{"name":"rotate35","parent":"rotator6","pivot":[5,2,12],"rotation":[0,150,0],"cubes":[{"origin":[8.90955,-13.2,6.50359],"size":[1,32,0],"uv":[62,0]}]},{"name":"rotate36","parent":"rotator6","pivot":[5,2,12],"rotation":[0,180,0]},{"name":"dulo2","pivot":[20,11,0],"rotation":[-90,-90,0]},{"name":"dulo4","parent":"dulo2","pivot":[19,11,8],"rotation":[0,-15,0]},{"name":"rotator7","parent":"dulo4","pivot":[20,11,4]},{"name":"rotate37","parent":"rotator7","pivot":[20,11,4],"rotation":[0,30,0],"cubes":[{"origin":[16.7866,40.8,6.06577],"size":[1,3,4.5],"uv":[62,0]}]},{"name":"rotate38","parent":"rotator7","pivot":[21,11,4],"rotation":[0,60,0],"cubes":[{"origin":[16.30026,40.8,3.48135],"size":[1,3,4.5],"uv":[62,0]}]},{"name":"rotate39","parent":"rotator7","pivot":[23,11,4],"rotation":[0,90,0],"cubes":[{"origin":[18.80526,40.8,-0.63397],"size":[1,3,4.5],"uv":[62,0]}]},{"name":"rotate40","parent":"rotator7","pivot":[26,11,4],"rotation":[0,120,0],"cubes":[{"origin":[25.80026,40.8,-4.54352],"size":[1,3,4.5],"uv":[62,0]}]},{"name":"rotate41","parent":"rotator7","pivot":[26,11,4],"rotation":[0,150,0],"cubes":[{"origin":[29.71481,40.8,-3.33372],"size":[1,3,4.5],"uv":[62,0]}]},{"name":"rotate42","parent":"rotator7","pivot":[26,11,4],"rotation":[0,180,0],"cubes":[{"origin":[32.5,40.8,-0.32872],"size":[1,3,4.5],"uv":[62,0]}]},{"name":"rotator8","parent":"dulo4","pivot":[18,11,-1],"rotation":[0,180,0]},{"name":"rotate43","parent":"rotator8","pivot":[19,11,-1],"rotation":[0,30,0],"cubes":[{"origin":[21.11532,40.8,-10.16385],"size":[1,3,4.5],"uv":[62,0]}]},{"name":"rotate44","parent":"rotator8","pivot":[21,11,-1],"rotation":[0,60,0],"cubes":[{"origin":[26.02987,40.8,-9.44545],"size":[1,3,4.5],"uv":[62,0]}]},{"name":"rotate45","parent":"rotator8","pivot":[24,11,-1],"rotation":[0,90,0],"cubes":[{"origin":[32.19474,40.8,-8.63397],"size":[1,3,4.5],"uv":[62,0]}]},{"name":"rotate46","parent":"rotator8","pivot":[24,11,-1],"rotation":[0,120,0],"cubes":[{"origin":[34.52987,40.8,-3.34878],"size":[1,3,4.5],"uv":[62,0]}]},{"name":"rotate47","parent":"rotator8","pivot":[24,11,-1],"rotation":[0,150,0],"cubes":[{"origin":[33.90955,40.8,2.3959],"size":[1,3,4.5],"uv":[62,0]}]},{"name":"rotate48","parent":"rotator8","pivot":[24,11,-1],"rotation":[0,180,0],"cubes":[{"origin":[30.5,40.8,7.06077],"size":[1,3,4.5],"uv":[62,0]}]},{"name":"rotator3","parent":"dulo2","pivot":[20,11,4]},{"name":"rotate5","parent":"rotator3","pivot":[20,11,4],"rotation":[0,30,0],"cubes":[{"origin":[16.7866,40.8,6.06577],"size":[1,3,4.5],"uv":[62,0]}]},{"name":"rotate6","parent":"rotator3","pivot":[21,11,4],"rotation":[0,60,0],"cubes":[{"origin":[16.30026,40.8,3.48135],"size":[1,3,4.5],"uv":[62,0]}]},{"name":"rotate7","parent":"rotator3","pivot":[23,11,4],"rotation":[0,90,0],"cubes":[{"origin":[18.80526,40.8,-0.63397],"size":[1,3,4.5],"uv":[62,0]}]},{"name":"rotate8","parent":"rotator3","pivot":[26,11,4],"rotation":[0,120,0],"cubes":[{"origin":[25.80026,40.8,-4.54352],"size":[1,3,4.5],"uv":[62,0]}]},{"name":"rotate11","parent":"rotator3","pivot":[26,11,4],"rotation":[0,150,0],"cubes":[{"origin":[29.71481,40.8,-3.33372],"size":[1,3,4.5],"uv":[62,0]}]},{"name":"rotate18","parent":"rotator3","pivot":[26,11,4],"rotation":[0,180,0],"cubes":[{"origin":[32.5,40.8,-0.32872],"size":[1,3,4.5],"uv":[62,0]}]},{"name":"rotator4","parent":"dulo2","pivot":[18,11,-1],"rotation":[0,180,0]},{"name":"rotate19","parent":"rotator4","pivot":[19,11,-1],"rotation":[0,30,0],"cubes":[{"origin":[21.11532,40.8,-10.16385],"size":[1,3,4.5],"uv":[62,0]}]},{"name":"rotate20","parent":"rotator4","pivot":[21,11,-1],"rotation":[0,60,0],"cubes":[{"origin":[26.02987,40.8,-9.44545],"size":[1,3,4.5],"uv":[62,0]}]},{"name":"rotate21","parent":"rotator4","pivot":[24,11,-1],"rotation":[0,90,0],"cubes":[{"origin":[32.19474,40.8,-8.63397],"size":[1,3,4.5],"uv":[62,0]}]},{"name":"rotate22","parent":"rotator4","pivot":[24,11,-1],"rotation":[0,120,0],"cubes":[{"origin":[34.52987,40.8,-3.34878],"size":[1,3,4.5],"uv":[62,0]}]},{"name":"rotate23","parent":"rotator4","pivot":[24,11,-1],"rotation":[0,150,0],"cubes":[{"origin":[33.90955,40.8,2.3959],"size":[1,3,4.5],"uv":[62,0]}]},{"name":"rotate24","parent":"rotator4","pivot":[24,11,-1],"rotation":[0,180,0],"cubes":[{"origin":[30.5,40.8,7.06077],"size":[1,3,4.5],"uv":[62,0]}]},{"name":"dulo5","pivot":[20,11,0],"rotation":[-90,-90,0]},{"name":"dulo6","parent":"dulo5","pivot":[19,11,8],"rotation":[0,-15,0]},{"name":"rotator9","parent":"dulo6","pivot":[20,11,4]},{"name":"rotate49","parent":"rotator9","pivot":[20,11,4],"rotation":[0,30,0],"cubes":[{"origin":[16.7866,17.8,6.06577],"size":[1,3,4.5],"uv":[62,0]}]},{"name":"rotate50","parent":"rotator9","pivot":[21,11,4],"rotation":[0,60,0],"cubes":[{"origin":[16.30026,17.8,3.48135],"size":[1,3,4.5],"uv":[62,0]}]},{"name":"rotate51","parent":"rotator9","pivot":[23,11,4],"rotation":[0,90,0],"cubes":[{"origin":[18.80526,17.8,-0.63397],"size":[1,3,4.5],"uv":[62,0]}]},{"name":"rotate52","parent":"rotator9","pivot":[26,11,4],"rotation":[0,120,0],"cubes":[{"origin":[25.80026,17.8,-4.54352],"size":[1,3,4.5],"uv":[62,0]}]},{"name":"rotate53","parent":"rotator9","pivot":[26,11,4],"rotation":[0,150,0],"cubes":[{"origin":[29.71481,17.8,-3.33372],"size":[1,3,4.5],"uv":[62,0]}]},{"name":"rotate54","parent":"rotator9","pivot":[26,11,4],"rotation":[0,180,0],"cubes":[{"origin":[32.5,17.8,-0.32872],"size":[1,3,4.5],"uv":[62,0]}]},{"name":"rotator10","parent":"dulo6","pivot":[18,11,-1],"rotation":[0,180,0]},{"name":"rotate55","parent":"rotator10","pivot":[19,11,-1],"rotation":[0,30,0],"cubes":[{"origin":[21.11532,17.8,-10.16385],"size":[1,3,4.5],"uv":[62,0]}]},{"name":"rotate56","parent":"rotator10","pivot":[21,11,-1],"rotation":[0,60,0],"cubes":[{"origin":[26.02987,17.8,-9.44545],"size":[1,3,4.5],"uv":[62,0]}]},{"name":"rotate57","parent":"rotator10","pivot":[24,11,-1],"rotation":[0,90,0],"cubes":[{"origin":[32.19474,17.8,-8.63397],"size":[1,3,4.5],"uv":[62,0]}]},{"name":"rotate58","parent":"rotator10","pivot":[24,11,-1],"rotation":[0,120,0],"cubes":[{"origin":[34.52987,17.8,-3.34878],"size":[1,3,4.5],"uv":[62,0]}]},{"name":"rotate59","parent":"rotator10","pivot":[24,11,-1],"rotation":[0,150,0],"cubes":[{"origin":[33.90955,17.8,2.3959],"size":[1,3,4.5],"uv":[62,0]}]},{"name":"rotate60","parent":"rotator10","pivot":[24,11,-1],"rotation":[0,180,0],"cubes":[{"origin":[30.5,17.8,7.06077],"size":[1,3,4.5],"uv":[62,0]}]},{"name":"rotator11","parent":"dulo5","pivot":[20,11,4]},{"name":"rotate61","parent":"rotator11","pivot":[20,11,4],"rotation":[0,30,0],"cubes":[{"origin":[16.7866,17.8,6.06577],"size":[1,3,4.5],"uv":[62,0]}]},{"name":"rotate62","parent":"rotator11","pivot":[21,11,4],"rotation":[0,60,0],"cubes":[{"origin":[16.30026,17.8,3.48135],"size":[1,3,4.5],"uv":[62,0]}]},{"name":"rotate63","parent":"rotator11","pivot":[23,11,4],"rotation":[0,90,0],"cubes":[{"origin":[18.80526,17.8,-0.63397],"size":[1,3,4.5],"uv":[62,0]}]},{"name":"rotate64","parent":"rotator11","pivot":[26,11,4],"rotation":[0,120,0],"cubes":[{"origin":[25.80026,17.8,-4.54352],"size":[1,3,4.5],"uv":[62,0]}]},{"name":"rotate65","parent":"rotator11","pivot":[26,11,4],"rotation":[0,150,0],"cubes":[{"origin":[29.71481,17.8,-3.33372],"size":[1,3,4.5],"uv":[62,0]}]},{"name":"rotate66","parent":"rotator11","pivot":[26,11,4],"rotation":[0,180,0],"cubes":[{"origin":[32.5,17.8,-0.32872],"size":[1,3,4.5],"uv":[62,0]}]},{"name":"rotator12","parent":"dulo5","pivot":[18,11,-1],"rotation":[0,180,0]},{"name":"rotate67","parent":"rotator12","pivot":[19,11,-1],"rotation":[0,30,0],"cubes":[{"origin":[21.11532,17.8,-10.16385],"size":[1,3,4.5],"uv":[62,0]}]},{"name":"rotate68","parent":"rotator12","pivot":[21,11,-1],"rotation":[0,60,0],"cubes":[{"origin":[26.02987,17.8,-9.44545],"size":[1,3,4.5],"uv":[62,0]}]},{"name":"rotate69","parent":"rotator12","pivot":[24,11,-1],"rotation":[0,90,0],"cubes":[{"origin":[32.19474,17.8,-8.63397],"size":[1,3,4.5],"uv":[62,0]}]},{"name":"rotate70","parent":"rotator12","pivot":[24,11,-1],"rotation":[0,120,0],"cubes":[{"origin":[34.52987,17.8,-3.34878],"size":[1,3,4.5],"uv":[62,0]}]},{"name":"rotate71","parent":"rotator12","pivot":[24,11,-1],"rotation":[0,150,0],"cubes":[{"origin":[33.90955,17.8,2.3959],"size":[1,3,4.5],"uv":[62,0]}]},{"name":"rotate72","parent":"rotator12","pivot":[24,11,-1],"rotation":[0,180,0],"cubes":[{"origin":[30.5,17.8,7.06077],"size":[1,3,4.5],"uv":[62,0]}]}]}]}